Workbook

Sheet 00 ACC DETAILS 01
B2: ACCOUNT DETAILS | F2: REQUESTED BY
B3: Lot No. | C3: 2512-C-10B | F3: Name of Requester
B4: Division | C4: 10 | F4: First Name | G4: =IF(ISBLANK(C6),C11,C7)
B5: Name of IA | C5: BAGONG BUHAY IA | F5: Middle Name | G5: =IF(ISBLANK(C6),C12,C8)
A6: * | B6: Name of Land Owner | F6: Surname | G6: =IF(ISBLANK(C6),C13,C9)
B7: First Name | C7: TIBURCIO | F7: Address of Requester
B8: Middle Name | F8: Barangay | G8: =IF(ISBLANK(C6),C23,C19)
B9: Surname | C9: PUNZALAN | F9: Municipality/City | G9: =IF(ISBLANK(C6),C24,C20)
B10: Name of Farmer/Land Tiller | F10: Province | G10: =IF(ISBLANK(C6),C25,C21)
B11: First Name | C11: FERNANDO
B12: Middle Name
B13: Surname | C13: SILVESTRE
B14: Location of Lot
B15: Baranggay
B16: Municipality/City
B17: Province
B18: Address of Land Owner
B19: Barangay
B20: Municipality/City
B21: Province
B22: Address of Farmer/Land Tiller
B23: Baranggay
B24: Municipality/City
B25: Province
A28: IRRIGATION FEE REGISTRY (IFR)
B29: Wet/Dry | C29: Year | D29: Area
A30: 1 | B30: DRY | C30: 1975 | D30: 0.47 | E30: =IF(ISBLANK(B30),0,IF(C30<2000,RIGHT(C30,2),C30)&"-"&IF(B30="wet","W","D"))
A31: 2 | B31: DRY | C31: 1976 | D31: 0.47 | E31: =IF(ISBLANK(B31),0,IF(C31<2000,RIGHT(C31,2),C31)&"-"&IF(B31="wet","W","D"))
A32: 3 | B32: DRY | C32: 1977 | D32: 0.47 | E32: =IF(ISBLANK(B32),0,IF(C32<2000,RIGHT(C32,2),C32)&"-"&IF(B32="wet","W","D"))
A33: 4 | B33: DRY | C33: 1978 | D33: 0.47 | E33: =IF(ISBLANK(B33),0,IF(C33<2000,RIGHT(C33,2),C33)&"-"&IF(B33="wet","W","D"))
A34: 5 | B34: DRY | C34: 1979 | D34: 0.47 | E34: =IF(ISBLANK(B34),0,IF(C34<2000,RIGHT(C34,2),C34)&"-"&IF(B34="wet","W","D"))
A35: 6 | B35: DRY | C35: 1980 | D35: 0.47 | E35: =IF(ISBLANK(B35),0,IF(C35<2000,RIGHT(C35,2),C35)&"-"&IF(B35="wet","W","D"))
A36: 7 | B36: DRY | C36: 1981 | D36: 0.47 | E36: =IF(ISBLANK(B36),0,IF(C36<2000,RIGHT(C36,2),C36)&"-"&IF(B36="wet","W","D"))
A37: 8 | B37: DRY | C37: 1982 | D37: 0.47 | E37: =IF(ISBLANK(B37),0,IF(C37<2000,RIGHT(C37,2),C37)&"-"&IF(B37="wet","W","D"))
A38: 9 | B38: DRY | C38: 1983 | D38: 0.47 | E38: =IF(ISBLANK(B38),0,IF(C38<2000,RIGHT(C38,2),C38)&"-"&IF(B38="wet","W","D"))
A39: 10 | B39: DRY | C39: 1984 | D39: 0.47 | E39: =IF(ISBLANK(B39),0,IF(C39<2000,RIGHT(C39,2),C39)&"-"&IF(B39="wet","W","D"))
A40: 11 | B40: DRY | C40: 1985 | D40: 0.47 | E40: =IF(ISBLANK(B40),0,IF(C40<2000,RIGHT(C40,2),C40)&"-"&IF(B40="wet","W","D"))
A41: 12 | B41: DRY | C41: 1986 | D41: 0.47 | E41: =IF(ISBLANK(B41),0,IF(C41<2000,RIGHT(C41,2),C41)&"-"&IF(B41="wet","W","D"))
... A66: 37 | B66: DRY | C66: 2012 | D66: 0.47 | E66: =IF(ISBLANK(B66),0,IF(C66<2000,RIGHT(C66,2),C66)&"-"&IF(B66="wet","W","D"))
A67: 38 | E67: =IF(ISBLANK(B67),0,IF(C67<2000,RIGHT(C67,2),C67)&"-"&IF(B67="wet","W","D"))
A68: 39 | E68: =IF(ISBLANK(B68),0,IF(C68<2000,RIGHT(C68,2),C68)&"-"&IF(B68="wet","W","D"))
A69: 40 | E69: =IF(ISBLANK(B69),0,IF(C69<2000,RIGHT(C69,2),C69)&"-"&IF(B69="wet","W","D"))
A70: 41 | E70: =IF(ISBLANK(B70),0,IF(C70<2000,RIGHT(C70,2),C70)&"-"&IF(B70="wet","W","D"))
A71: 42 | E71: =IF(ISBLANK(B71),0,IF(C71<2000,RIGHT(C71,2),C71)&"-"&IF(B71="wet","W","D"))
A72: 43 | E72: =IF(ISBLANK(B72),0,IF(C72<2000,RIGHT(C72,2),C72)&"-"&IF(B72="wet","W","D"))
A73: 44 | E73: =IF(ISBLANK(B73),0,IF(C73<2000,RIGHT(C73,2),C73)&"-"&IF(B73="wet","W","D"))
A74: 45 | E74: =IF(ISBLANK(B74),0,IF(C74<2000,RIGHT(C74,2),C74)&"-"&IF(B74="wet","W","D"))
A75: 46 | E75: =IF(ISBLANK(B75),0,IF(C75<2000,RIGHT(C75,2),C75)&"-"&IF(B75="wet","W","D"))
A76: 47 | E76: =IF(ISBLANK(B76),0,IF(C76<2000,RIGHT(C76,2),C76)&"-"&IF(B76="wet","W","D"))
A77: 48 | E77: =IF(ISBLANK(B77),0,IF(C77<2000,RIGHT(C77,2),C77)&"-"&IF(B77="wet","W","D"))
A78: 49 | E78: =IF(ISBLANK(B78),0,IF(C78<2000,RIGHT(C78,2),C78)&"-"&IF(B78="wet","W","D"))
... A112: 83 | E112: =IF(ISBLANK(B112),0,IF(C112<2000,RIGHT(C112,2),C112)&"-"&IF(B112="wet","W","D"))

Sheet 01 SOA 01
A2: REPUBLIC OF THE PHILIPPINES
A3: NATIONAL IRRIGATION ADMINISTRATION
A4: REGIONAL OFFICE NO. III (CENTRAL LUZON)
A5: BULACAN IRRIGATION MANAGEMENT OFFICE
A9: STATEMENT OF ACCOUNT
A10: ="as of "&TEXT(TODAY(),"mmmm dd, yyyy")
A12: FARMER CODE NO.: | F12: WRFT Div. : | G12: ='00 ACC DETAILS 01'!C4&" - "&'00 ACC DETAILS 01'!C5
A13: Lot No.: | C13: ='00 ACC DETAILS 01'!C3 | F13: Area:. | G13: {=LOOKUP(2,0/(A17:A99),A17:A99)}
A14: Name of Landowner: | C14: =IF(ISBLANK('00 ACC DETAILS 01'!C8),'00 ACC DETAILS 01'!C7&" "&'00 ACC DETAILS 01'!C9,'00 ACC DETAILS 01'!C7&" "&'00 ACC DETAILS 01'!C8&" "&'00 ACC DETAILS 01'!C9) | E14: Address:
A15: Name of Farmers: | C15: =IF(ISBLANK('00 ACC DETAILS 01'!C12),'00 ACC DETAILS 01'!C11&" "&'00 ACC DETAILS 01'!C13,'00 ACC DETAILS 01'!C11&" "&'00 ACC DETAILS 01'!C12&" "&'00 ACC DETAILS 01'!C13) | E15: Address:
A16: Area | B16: C. S. | C16: Rate | D16: Principal | E16: %Penalty | F16: Penalty(Cash) | G16: Total
A17: =IFERROR((LOOKUP(MATCH(B17,'00 ACC DETAILS 01'!$E$30:$E$112,0),'00 ACC DETAILS 01'!$A$30:$A$112,'00 ACC DETAILS 01'!$D$30:$D$112)),0) | B17: 75-W | C17: =15*100 | D17: =A17*C17 | E17: =E19+12 | F17: =D17*E17/100 | G17: =D17+F17
A18: =IFERROR((LOOKUP(MATCH(B18,'00 ACC DETAILS 01'!$E$30:$E$112,0),'00 ACC DETAILS 01'!$A$30:$A$112,'00 ACC DETAILS 01'!$D$30:$D$112)),0) | B18: 76-D | C18: =15*150 | D18: =A18*C18 | E18: =E20+12 | F18: =D18*E18/100 | G18: =D18+F18
A19: =IFERROR((LOOKUP(MATCH(B19,'00 ACC DETAILS 01'!$E$30:$E$112,0),'00 ACC DETAILS 01'!$A$30:$A$112,'00 ACC DETAILS 01'!$D$30:$D$112)),0) | B19: 76-W | C19: =C17 | D19: =A19*C19 | E19: =E20+12 | F19: =D19*E19/100 | G19: =D19+F19
A20: =IFERROR((LOOKUP(MATCH(B20,'00 ACC DETAILS 01'!$E$30:$E$112,0),'00 ACC DETAILS 01'!$A$30:$A$112,'00 ACC DETAILS 01'!$D$30:$D$112)),0) | B20: 77-D | C20: =C18 | D20: =A20*C20 | E20: =E22+12 | F20: =D20*E20/100 | G20: =D20+F20
A21: =IFERROR((LOOKUP(MATCH(B21,'00 ACC DETAILS 01'!$E$30:$E$112,0),'00 ACC DETAILS 01'!$A$30:$A$112,'00 ACC DETAILS 01'!$D$30:$D$112)),0) | B21: 77-W | C21: =C19 | D21: =A21*C21 | E21: =E22+12 | F21: =D21*E21/100 | G21: =D21+F21
A22: =IFERROR((LOOKUP(MATCH(B22,'00 ACC DETAILS 01'!$E$30:$E$112,0),'00 ACC DETAILS 01'!$A$30:$A$112,'00 ACC DETAILS 01'!$D$30:$D$112)),0) | B22: 78-D | C22: =C20 | D22: =A22*C22 | E22: =E24+6 | F22: =D22*E22/100 | G22: =D22+F22
A23: =IFERROR((LOOKUP(MATCH(B23,'00 ACC DETAILS 01'!$E$30:$E$112,0),'00 ACC DETAILS 01'!$A$30:$A$112,'00 ACC DETAILS 01'!$D$30:$D$112)),0) | B23: 78-W | C23: =C21 | D23: =A23*C23 | E23: =E24+6 | F23: =D23*E23/100 | G23: =D23+F23
A24: =IFERROR((LOOKUP(MATCH(B24,'00 ACC DETAILS 01'!$E$30:$E$112,0),'00 ACC DETAILS 01'!$A$30:$A$112,'00 ACC DETAILS 01'!$D$30:$D$112)),0) | B24: 79-D | C24: =C22 | D24: =A24*C24 | E24: =E25+6 | F24: =D24*E24/100 | G24: =D24+F24
A25: =IFERROR((LOOKUP(MATCH(B25,'00 ACC DETAILS 01'!$E$30:$E$112,0),'00 ACC DETAILS 01'!$A$30:$A$112,'00 ACC DETAILS 01'!$D$30:$D$112)),0) | B25: 79-W | C25: =C23 | D25: =A25*C25 | E25: =E26+6 | F25: =D25*E25/100 | G25: =D25+F25
A26: =IFERROR((LOOKUP(MATCH(B26,'00 ACC DETAILS 01'!$E$30:$E$112,0),'00 ACC DETAILS 01'!$A$30:$A$112,'00 ACC DETAILS 01'!$D$30:$D$112)),0) | B26: 80-D | C26: =C24 | D26: =A26*C26 | E26: =E27+6 | F26: =D26*E26/100 | G26: =D26+F26
A27: =IFERROR((LOOKUP(MATCH(B27,'00 ACC DETAILS 01'!$E$30:$E$112,0),'00 ACC DETAILS 01'!$A$30:$A$112,'00 ACC DETAILS 01'!$D$30:$D$112)),0) | B27: 80-W | C27: =C25 | D27: =A27*C27 | E27: =E28+6 | F27: =D27*E27/100 | G27: =D27+F27
A28: =IFERROR((LOOKUP(MATCH(B28,'00 ACC DETAILS 01'!$E$30:$E$112,0),'00 ACC DETAILS 01'!$A$30:$A$112,'00 ACC DETAILS 01'!$D$30:$D$112)),0) | B28: 81-D | C28: =C26 | D28: =A28*C28 | E28: =E29+6 | F28: =D28*E28/100 | G28: =D28+F28
A29: =IFERROR((LOOKUP(MATCH(B29,'00 ACC DETAILS 01'!$E$30:$E$112,0),'00 ACC DETAILS 01'!$A$30:$A$112,'00 ACC DETAILS 01'!$D$30:$D$112)),0) | B29: 81-W | C29: =C27 | D29: =A29*C29 | E29: =E30+6 | F29: =D29*E29/100 | G29: =D29+F29
A30: =IFERROR((LOOKUP(MATCH(B30,'00 ACC DETAILS 01'!$E$30:$E$112,0),'00 ACC DETAILS 01'!$A$30:$A$112,'00 ACC DETAILS 01'!$D$30:$D$112)),0) | B30: 82-D | C30: =C28 | D30: =A30*C30 | E30: =E31+6 | F30: =D30*E30/100 | G30: =D30+F30
A31: =IFERROR((LOOKUP(MATCH(B31,'00 ACC DETAILS 01'!$E$30:$E$112,0),'00 ACC DETAILS 01'!$A$30:$A$112,'00 ACC DETAILS 01'!$D$30:$D$112)),0) | B31: 82-W | C31: =C29 | D31: =A31*C31 | E31: =E32+6 | F31: =D31*E31/100 | G31: =D31+F31
A32: =IFERROR((LOOKUP(MATCH(B32,'00 ACC DETAILS 01'!$E$30:$E$112,0),'00 ACC DETAILS 01'!$A$30:$A$112,'00 ACC DETAILS 01'!$D$30:$D$112)),0) | B32: 83-D | C32: =C30 | D32: =A32*C32 | E32: =E33+6 | F32: =D32*E32/100 | G32: =D32+F32
A33: =IFERROR((LOOKUP(MATCH(B33,'00 ACC DETAILS 01'!$E$30:$E$112,0),'00 ACC DETAILS 01'!$A$30:$A$112,'00 ACC DETAILS 01'!$D$30:$D$112)),0) | B33: 83-W | C33: =C31 | D33: =A33*C33 | E33: =E34+6 | F33: =D33*E33/100 | G33: =D33+F33
A34: =IFERROR((LOOKUP(MATCH(B34,'00 ACC DETAILS 01'!$E$30:$E$112,0),'00 ACC DETAILS 01'!$A$30:$A$112,'00 ACC DETAILS 01'!$D$30:$D$112)),0) | B34: 84-D | C34: =C32 | D34: =A34*C34 | E34: =E35+6 | F34: =D34*E34/100 | G34: =D34+F34
... A61: =IFERROR((LOOKUP(MATCH(B61,'00 ACC DETAILS 01'!$E$30:$E$112,0),'00 ACC DETAILS 01'!$A$30:$A$112,'00 ACC DETAILS 01'!$D$30:$D$112)),0) | B61: 97-W | C61: =C59 | D61: =A61*C61 | E61: =E62+6 | F61: =D61*E61/100 | G61: =D61+F61
A62: =IFERROR((LOOKUP(MATCH(B62,'00 ACC DETAILS 01'!$E$30:$E$112,0),'00 ACC DETAILS 01'!$A$30:$A$112,'00 ACC DETAILS 01'!$D$30:$D$112)),0) | B62: 98-D | C62: 0 | D62: =A62*C62 | E62: =E63+6 | F62: =D62*E62/100 | G62: =D62+F62
A63: =IFERROR((LOOKUP(MATCH(B63,'00 ACC DETAILS 01'!$E$30:$E$112,0),'00 ACC DETAILS 01'!$A$30:$A$112,'00 ACC DETAILS 01'!$D$30:$D$112)),0) | B63: 98-W | C63: 400 | D63: =A63*C63 | E63: =E64+6 | F63: =D63*E63/100 | G63: =D63+F63
A64: =IFERROR((LOOKUP(MATCH(B64,'00 ACC DETAILS 01'!$E$30:$E$112,0),'00 ACC DETAILS 01'!$A$30:$A$112,'00 ACC DETAILS 01'!$D$30:$D$112)),0) | B64: 99-D | C64: 600 | D64: =A64*C64 | E64: =E65+6 | F64: =D64*E64/100 | G64: =D64+F64
A65: =IFERROR((LOOKUP(MATCH(B65,'00 ACC DETAILS 01'!$E$30:$E$112,0),'00 ACC DETAILS 01'!$A$30:$A$112,'00 ACC DETAILS 01'!$D$30:$D$112)),0) | B65: 99-W | C65: 450 | D65: =A65*C65 | E65: =E66+6 | F65: =D65*E65/100 | G65: =D65+F65
A66: =IFERROR((LOOKUP(MATCH(B66,'00 ACC DETAILS 01'!$E$30:$E$112,0),'00 ACC DETAILS 01'!$A$30:$A$112,'00 ACC DETAILS 01'!$D$30:$D$112)),0) | B66: 2000-D | C66: 750 | D66: =A66*C66 | E66: =E67+6 | F66: =D66*E66/100 | G66: =D66+F66
A67: =IFERROR((LOOKUP(MATCH(B67,'00 ACC DETAILS 01'!$E$30:$E$112,0),'00 ACC DETAILS 01'!$A$30:$A$112,'00 ACC DETAILS 01'!$D$30:$D$112)),0) | B67: 2000-W | C67: =C65 | D67: =A67*C67 | E67: =E68+6 | F67: =D67*E67/100 | G67: =D67+F67
A68: =IFERROR((LOOKUP(MATCH(B68,'00 ACC DETAILS 01'!$E$30:$E$112,0),'00 ACC DETAILS 01'!$A$30:$A$112,'00 ACC DETAILS 01'!$D$30:$D$112)),0) | B68: 2001-D | C68: =C66 | D68: =A68*C68 | E68: =E69+6 | F68: =D68*E68/100 | G68: =D68+F68
A69: =IFERROR((LOOKUP(MATCH(B69,'00 ACC DETAILS 01'!$E$30:$E$112,0),'00 ACC DETAILS 01'!$A$30:$A$112,'00 ACC DETAILS 01'!$D$30:$D$112)),0) | B69: 2001-W | C69: =C61 | D69: =A69*C69 | E69: =E70+6 | F69: =D69*E69/100 | G69: =D69+F69
A70: =IFERROR((LOOKUP(MATCH(B70,'00 ACC DETAILS 01'!$E$30:$E$112,0),'00 ACC DETAILS 01'!$A$30:$A$112,'00 ACC DETAILS 01'!$D$30:$D$112)),0) | B70: 2002-D | C70: =C60 | D70: =A70*C70 | E70: =E71+6 | F70: =D70*E70/100 | G70: =D70+F70
A71: =IFERROR((LOOKUP(MATCH(B71,'00 ACC DETAILS 01'!$E$30:$E$112,0),'00 ACC DETAILS 01'!$A$30:$A$112,'00 ACC DETAILS 01'!$D$30:$D$112)),0) | B71: 2002-W | C71: =C69 | D71: =A71*C71 | E71: =E72+6 | F71: =D71*E71/100 | G71: =D71+F71
A72: =IFERROR((LOOKUP(MATCH(B72,'00 ACC DETAILS 01'!$E$30:$E$112,0),'00 ACC DETAILS 01'!$A$30:$A$112,'00 ACC DETAILS 01'!$D$30:$D$112)),0) | B72: 2003-D | C72: =C70 | D72: =A72*C72 | E72: =E73+6 | F72: =D72*E72/100 | G72: =D72+F72
A73: =IFERROR((LOOKUP(MATCH(B73,'00 ACC DETAILS 01'!$E$30:$E$112,0),'00 ACC DETAILS 01'!$A$30:$A$112,'00 ACC DETAILS 01'!$D$30:$D$112)),0) | B73: 2003-W | C73: =C71 | D73: =A73*C73 | E73: =E74+6 | F73: =D73*E73/100 | G73: =D73+F73
A74: =IFERROR((LOOKUP(MATCH(B74,'00 ACC DETAILS 01'!$E$30:$E$112,0),'00 ACC DETAILS 01'!$A$30:$A$112,'00 ACC DETAILS 01'!$D$30:$D$112)),0) | B74: 2004-D | C74: =C72 | D74: =A74*C74 | E74: =E75+6 | F74: =D74*E74/100 | G74: =D74+F74
A75: =IFERROR((LOOKUP(MATCH(B75,'00 ACC DETAILS 01'!$E$30:$E$112,0),'00 ACC DETAILS 01'!$A$30:$A$112,'00 ACC DETAILS 01'!$D$30:$D$112)),0) | B75: 2004-W | C75: =C73 | D75: =A75*C75 | E75: =E76+6 | F75: =D75*E75/100 | G75: =D75+F75
A76: =IFERROR((LOOKUP(MATCH(B76,'00 ACC DETAILS 01'!$E$30:$E$112,0),'00 ACC DETAILS 01'!$A$30:$A$112,'00 ACC DETAILS 01'!$D$30:$D$112)),0) | B76: 2005-D | C76: =C74 | D76: =A76*C76 | E76: =E77+6 | F76: =D76*E76/100 | G76: =D76+F76
A77: =IFERROR((LOOKUP(MATCH(B77,'00 ACC DETAILS 01'!$E$30:$E$112,0),'00 ACC DETAILS 01'!$A$30:$A$112,'00 ACC DETAILS 01'!$D$30:$D$112)),0) | B77: 2005-W | C77: =C75 | D77: =A77*C77 | E77: =E78+6 | F77: =D77*E77/100 | G77: =D77+F77
A78: =IFERROR((LOOKUP(MATCH(B78,'00 ACC DETAILS 01'!$E$30:$E$112,0),'00 ACC DETAILS 01'!$A$30:$A$112,'00 ACC DETAILS 01'!$D$30:$D$112)),0) | B78: 2006-D | C78: =C76 | D78: =A78*C78 | E78: =E79+6 | F78: =D78*E78/100 | G78: =D78+F78
A79: =IFERROR((LOOKUP(MATCH(B79,'00 ACC DETAILS 01'!$E$30:$E$112,0),'00 ACC DETAILS 01'!$A$30:$A$112,'00 ACC DETAILS 01'!$D$30:$D$112)),0) | B79: 2006-W | C79: =C77 | D79: =A79*C79 | E79: =E80+6 | F79: =D79*E79/100 | G79: =D79+F79
A80: =IFERROR((LOOKUP(MATCH(B80,'00 ACC DETAILS 01'!$E$30:$E$112,0),'00 ACC DETAILS 01'!$A$30:$A$112,'00 ACC DETAILS 01'!$D$30:$D$112)),0) | B80: 2007-D | C80: =C78 | D80: =A80*C80 | E80: =E81+6 | F80: =D80*E80/100 | G80: =D80+F80
A81: =IFERROR((LOOKUP(MATCH(B81,'00 ACC DETAILS 01'!$E$30:$E$112,0),'00 ACC DETAILS 01'!$A$30:$A$112,'00 ACC DETAILS 01'!$D$30:$D$112)),0) | B81: 2007-W | C81: =C79 | D81: =A81*C81 | E81: =E82+6 | F81: =D81*E81/100 | G81: =D81+F81
A82: =IFERROR((LOOKUP(MATCH(B82,'00 ACC DETAILS 01'!$E$30:$E$112,0),'00 ACC DETAILS 01'!$A$30:$A$112,'00 ACC DETAILS 01'!$D$30:$D$112)),0) | B82: 2008-D | C82: =C80 | D82: =A82*C82 | E82: =E83+6 | F82: =D82*E82/100 | G82: =D82+F82
A83: =IFERROR((LOOKUP(MATCH(B83,'00 ACC DETAILS 01'!$E$30:$E$112,0),'00 ACC DETAILS 01'!$A$30:$A$112,'00 ACC DETAILS 01'!$D$30:$D$112)),0) | B83: 2008-W | C83: =C81 | D83: =A83*C83 | E83: =E84+6 | F83: =D83*E83/100 | G83: =D83+F83
A84: =IFERROR((LOOKUP(MATCH(B84,'00 ACC DETAILS 01'!$E$30:$E$112,0),'00 ACC DETAILS 01'!$A$30:$A$112,'00 ACC DETAILS 01'!$D$30:$D$112)),0) | B84: 2009-D | C84: 2250 | D84: =A84*C84 | E84: =E85+6 | F84: =D84*E84/100 | G84: =D84+F84
A85: =IFERROR((LOOKUP(MATCH(B85,'00 ACC DETAILS 01'!$E$30:$E$112,0),'00 ACC DETAILS 01'!$A$30:$A$112,'00 ACC DETAILS 01'!$D$30:$D$112)),0) | B85: 2009-W | C85: =C83 | D85: =A85*C85 | E85: =E86+6 | F85: =D85*E85/100 | G85: =D85+F85
A86: =IFERROR((LOOKUP(MATCH(B86,'00 ACC DETAILS 01'!$E$30:$E$112,0),'00 ACC DETAILS 01'!$A$30:$A$112,'00 ACC DETAILS 01'!$D$30:$D$112)),0) | B86: 2010-D | C86: =C84 | D86: =A86*C86 | E86: =E87+6 | F86: =D86*E86/100 | G86: =D86+F86
A87: =IFERROR((LOOKUP(MATCH(B87,'00 ACC DETAILS 01'!$E$30:$E$112,0),'00 ACC DETAILS 01'!$A$30:$A$112,'00 ACC DETAILS 01'!$D$30:$D$112)),0) | B87: 2010-W | C87: =C85 | D87: =A87*C87 | E87: =E88+6 | F87: =D87*E87/100 | G87: =D87+F87
A88: =IFERROR((LOOKUP(MATCH(B88,'00 ACC DETAILS 01'!$E$30:$E$112,0),'00 ACC DETAILS 01'!$A$30:$A$112,'00 ACC DETAILS 01'!$D$30:$D$112)),0) | B88: 2011-D | C88: =C86 | D88: =A88*C88 | E88: =E89+6 | F88: =D88*E88/100 | G88: =D88+F88
A89: =IFERROR((LOOKUP(MATCH(B89,'00 ACC DETAILS 01'!$E$30:$E$112,0),'00 ACC DETAILS 01'!$A$30:$A$112,'00 ACC DETAILS 01'!$D$30:$D$112)),0) | B89: 2011-W | C89: =C87 | D89: =A89*C89 | E89: =E90+6 | F89: =D89*E89/100 | G89: =D89+F89
A90: =IFERROR((LOOKUP(MATCH(B90,'00 ACC DETAILS 01'!$E$30:$E$112,0),'00 ACC DETAILS 01'!$A$30:$A$112,'00 ACC DETAILS 01'!$D$30:$D$112)),0) | B90: 2012-D | C90: 2550 | D90: =A90*C90 | E90: =E91+6 | F90: =D90*E90/100 | G90: =D90+F90
A91: =IFERROR((LOOKUP(MATCH(B91,'00 ACC DETAILS 01'!$E$30:$E$112,0),'00 ACC DETAILS 01'!$A$30:$A$112,'00 ACC DETAILS 01'!$D$30:$D$112)),0) | B91: 2012-W | C91: 1700 | D91: =A91*C91 | E91: =E92+6 | F91: =D91*E91/100 | G91: =D91+F91
A92: =IFERROR((LOOKUP(MATCH(B92,'00 ACC DETAILS 01'!$E$30:$E$112,0),'00 ACC DETAILS 01'!$A$30:$A$112,'00 ACC DETAILS 01'!$D$30:$D$112)),0) | B92: 2013-D | C92: =17*150 | D92: =A92*C92 | E92: =E93+6 | F92: =D92*E92/100 | G92: =D92+F92
A93: =IFERROR((LOOKUP(MATCH(B93,'00 ACC DETAILS 01'!$E$30:$E$112,0),'00 ACC DETAILS 01'!$A$30:$A$112,'00 ACC DETAILS 01'!$D$30:$D$112)),0) | B93: 2013-W | C93: =17*100 | D93: =A93*C93 | E93: =E94+6 | F93: =D93*E93/100 | G93: =D93+F93
A94: =IFERROR((LOOKUP(MATCH(B94,'00 ACC DETAILS 01'!$E$30:$E$112,0),'00 ACC DETAILS 01'!$A$30:$A$112,'00 ACC DETAILS 01'!$D$30:$D$112)),0) | B94: 2014-D | C94: =C92 | D94: =A94*C94 | E94: =E95+6 | F94: =D94*E94/100 | G94: =D94+F94
A95: =IFERROR((LOOKUP(MATCH(B95,'00 ACC DETAILS 01'!$E$30:$E$112,0),'00 ACC DETAILS 01'!$A$30:$A$112,'00 ACC DETAILS 01'!$D$30:$D$112)),0) | B95: 2014-W | C95: =17*100 | D95: =A95*C95 | E95: =E96+6 | F95: =D95*E95/100 | G95: =D95+F95
A96: =IFERROR((LOOKUP(MATCH(B96,'00 ACC DETAILS 01'!$E$30:$E$112,0),'00 ACC DETAILS 01'!$A$30:$A$112,'00 ACC DETAILS 01'!$D$30:$D$112)),0) | B96: 2015-D | C96: =C94 | D96: =A96*C96 | E96: =E97+6 | F96: =D96*E96/100 | G96: =D96+F96
A97: =IFERROR((LOOKUP(MATCH(B97,'00 ACC DETAILS 01'!$E$30:$E$112,0),'00 ACC DETAILS 01'!$A$30:$A$112,'00 ACC DETAILS 01'!$D$30:$D$112)),0) | B97: 2015-W | C97: =17*100 | D97: =A97*C97 | E97: =E98+6 | F97: =D97*E97/100 | G97: =D97+F97
A98: =IFERROR((LOOKUP(MATCH(B98,'00 ACC DETAILS 01'!$E$30:$E$112,0),'00 ACC DETAILS 01'!$A$30:$A$112,'00 ACC DETAILS 01'!$D$30:$D$112)),0) | B98: 2016-D | C98: =C96 | D98: =A98*C98 | E98: =E99+6 | F98: =D98*E98/100 | G98: =D98+F98
A99: =IFERROR((LOOKUP(MATCH(B99,'00 ACC DETAILS 01'!$E$30:$E$112,0),'00 ACC DETAILS 01'!$A$30:$A$112,'00 ACC DETAILS 01'!$D$30:$D$112)),0) | B99: 2016-W | C99: =17*100 | D99: =A99*C99 | E99: 11 | F99: =D99*E99/100 | G99: =D99+F99
A100: Sub-total | D100: =SUM(D17:D99) | F100: =SUM(F17:F99) | G100: =SUM(G17:G99)
A101: Add old accounts: Prior to July 1,1975 | G101: 239.88
A102: TOTAL | G102: =G100+G101
A103: Note: If you have any problem with your account and our services, please feel free to see us in our office.
A105: Prepared by: | C105: Checked by: | D105: Recommending Approval: | G105: Approved:
A107: CATHERINE DC. AUSTRIA | C107: MAGNOLIA L. TAYAO | E107: LEOPOLDO Q. MANIEGO | G107: ROBERTO J. DELA CRUZ
A108: Accounting Proc. A | C108: Head, Billing Unit | E108: O&M Chief | G108: Manager, BULACAN IMO
A117: Republika ng Pilipinas
A118: National Irrigation Administration
A119: (Pambansang Pangasiwaan ng Patubig)
A120: Bulacan – Aurora – Nueva Ecija Irrigation Management Office
A121: Tambubong, San Rafael, Bulacan
A123: Office Address : Tambubong, San Rafael, Bulacan | G123: Telefax No. (044) 766-3888
A124: Telephone Nos. : (044) 766-3888 | G124: TIN No. 000-578-009-000
A125: Email Address : niabaneimoafs@yahoo.com
A127: STATEMENT OF ACCOUNT
A128: =A10
A130: FARMER CODE NO.: | C130: =C12 | F130: WRFT Div. : | G130: =G12
A131: Lot No.: | C131: =C13 | F131: Area:. | G131: =G13
A132: Name of Landowner: | E132: Address:
A133: Name of Farmers: | C133: =C15 | E133: Address:
A134: Area | B134: C. S. | C134: Rate | D134: Principal | E134: %Penalty | F134: Penalty(Cash) | G134: Total
A135: =A17 | B135: 75-W | C135: =1.1*100 | D135: =A135*C135 | F135: =D135*E135/100 | G135: =D135+F135
A136: =A18 | B136: 76-D | C136: =1.1*150 | D136: =A136*C136 | F136: =D136*E136/100 | G136: =D136+F136
A137: =A19 | B137: 76-W | C137: =1.1*100 | D137: =A137*C137 | F137: =D137*E137/100 | G137: =D137+F137
A138: =A20 | B138: 77-D | C138: =1.1*150 | D138: =A138*C138 | F138: =D138*E138/100 | G138: =D138+F138
A139: =A21 | B139: 77-W | C139: =1.1*100 | D139: =A139*C139 | F139: =D139*E139/100 | G139: =D139+F139
A140: =A22 | B140: 78-D | C140: =1.1*150 | D140: =A140*C140 | F140: =D140*E140/100 | G140: =D140+F140
A141: =A23 | B141: 78-W | C141: =1.1*100 | D141: =A141*C141 | F141: =D141*E141/100 | G141: =D141+F141
A142: =A24 | B142: 79-D | C142: =1.1*150 | D142: =A142*C142 | F142: =D142*E142/100 | G142: =D142+F142
A143: =A25 | B143: 79-W | C143: =1.3*100 | D143: =A143*C143 | F143: =D143*E143/100 | G143: =D143+F143
A144: =A26 | B144: 80-D | C144: =1.3*150 | D144: =A144*C144 | F144: =D144*E144/100 | G144: =D144+F144
...

Sheet 00 ACC DETAILS 02
B2: ACCOUNT DETAILS
B3: Lot No. | C3: 3809
B4: Division | C4: ='00 ACC DETAILS 01'!C4
B5: Name of IA | C5: ='00 ACC DETAILS 01'!C5
B6: Name of Land Owner
B7: First Name | C7: ='00 ACC DETAILS 01'!C7
B8: Middle Name | C8: ='00 ACC DETAILS 01'!C8
B9: Surname | C9: ='00 ACC DETAILS 01'!C9
B10: Name of Farmer/Land Tiller
B11: First Name | C11: MARCELO
B12: Middle Name
B13: Surname | C13: GUINTO
B14: Location of Lot
B15: Baranggay | C15: ='00 ACC DETAILS 01'!C15
B16: Municipality/City | C16: ='00 ACC DETAILS 01'!C16
B17: Province | C17: ='00 ACC DETAILS 01'!C17
B18: Address of Land Owner
B19: Baranggay | C19: ='00 ACC DETAILS 01'!C19
B20: Municipality/City | C20: ='00 ACC DETAILS 01'!C20
B21: Province | C21: ='00 ACC DETAILS 01'!C21
B22: Address of Farmer/Land Tiller
B23: Baranggay | C23: ='00 ACC DETAILS 01'!C23
B24: Municipality/City | C24: ='00 ACC DETAILS 01'!C24
B25: Province | C25: ='00 ACC DETAILS 01'!C25
A28: IRRIGATION FEE REGISTRY (IFR)
B29: Wet/Dry | C29: Year | D29: Area
A30: 1 | E30: =IF(ISBLANK(B30),0,IF(C30<2000,RIGHT(C30,2),C30)&"-"&IF(B30="wet","W","D"))
A31: 2 | E31: =IF(ISBLANK(B31),0,IF(C31<2000,RIGHT(C31,2),C31)&"-"&IF(B31="wet","W","D"))
A32: 3 | E32: =IF(ISBLANK(B32),0,IF(C32<2000,RIGHT(C32,2),C32)&"-"&IF(B32="wet","W","D"))
A33: 4 | E33: =IF(ISBLANK(B33),0,IF(C33<2000,RIGHT(C33,2),C33)&"-"&IF(B33="wet","W","D"))
A34: 5 | E34: =IF(ISBLANK(B34),0,IF(C34<2000,RIGHT(C34,2),C34)&"-"&IF(B34="wet","W","D"))
A35: 6 | E35: =IF(ISBLANK(B35),0,IF(C35<2000,RIGHT(C35,2),C35)&"-"&IF(B35="wet","W","D"))
A36: 7 | E36: =IF(ISBLANK(B36),0,IF(C36<2000,RIGHT(C36,2),C36)&"-"&IF(B36="wet","W","D"))
A37: 8 | E37: =IF(ISBLANK(B37),0,IF(C37<2000,RIGHT(C37,2),C37)&"-"&IF(B37="wet","W","D"))
A38: 9 | E38: =IF(ISBLANK(B38),0,IF(C38<2000,RIGHT(C38,2),C38)&"-"&IF(B38="wet","W","D"))
A39: 10 | E39: =IF(ISBLANK(B39),0,IF(C39<2000,RIGHT(C39,2),C39)&"-"&IF(B39="wet","W","D"))
A40: 11 | E40: =IF(ISBLANK(B40),0,IF(C40<2000,RIGHT(C40,2),C40)&"-"&IF(B40="wet","W","D"))
A41: 12 | E41: =IF(ISBLANK(B41),0,IF(C41<2000,RIGHT(C41,2),C41)&"-"&IF(B41="wet","W","D"))
... A112: 83 | E112: =IF(ISBLANK(B112),0,IF(C112<2000,RIGHT(C112,2),C112)&"-"&IF(B112="wet","W","D"))

Sheet 01 SOA 02
A11: STATEMENT OF ACCOUNT
A12: ="as of "&TEXT(TODAY(),"mmmm dd, yyyy")
A14: FARMER CODE NO.: | F14: WRFT Div. : | G14: ='00 ACC DETAILS 02'!C4&" - "&'00 ACC DETAILS 02'!C5
A15: Lot No.: | C15: ='00 ACC DETAILS 02'!C3 | F15: Area:. | G15: {=IFERROR(0,LOOKUP(2,1/(A19:A101),A19:A101))}
A16: Name of Landowner: | C16: =IF(ISBLANK('00 ACC DETAILS 01'!C8),'00 ACC DETAILS 01'!C7&" "&'00 ACC DETAILS 01'!C9,'00 ACC DETAILS 01'!C7&" "&'00 ACC DETAILS 01'!C8&" "&'00 ACC DETAILS 01'!C9) | E16: Address:
A17: Name of Farmers: | C17: =IF(ISBLANK('00 ACC DETAILS 02'!C12),'00 ACC DETAILS 02'!C11&" "&'00 ACC DETAILS 02'!C13,'00 ACC DETAILS 02'!C11&" "&'00 ACC DETAILS 02'!C12&" "&'00 ACC DETAILS 02'!C13) | E17: Address:
A18: Area | B18: C. S. | C18: Rate | D18: Principal | E18: %Penalty | F18: Penalty(Cash) | G18: Total
A19: =IFERROR((LOOKUP(MATCH(B19,'00 ACC DETAILS 02'!$E$30:$E$112,0),'00 ACC DETAILS 02'!$A$30:$A$112,'00 ACC DETAILS 02'!$D$30:$D$112)),0) | B19: 75-W | C19: =15*100 | D19: =A19*C19 | E19: =E21+12 | F19: =D19*E19/100 | G19: =D19+F19
A20: =IFERROR((LOOKUP(MATCH(B20,'00 ACC DETAILS 02'!$E$30:$E$112,0),'00 ACC DETAILS 02'!$A$30:$A$112,'00 ACC DETAILS 02'!$D$30:$D$112)),0) | B20: 76-D | C20: =15*150 | D20: =A20*C20 | E20: =E22+12 | F20: =D20*E20/100 | G20: =D20+F20
A21: =IFERROR((LOOKUP(MATCH(B21,'00 ACC DETAILS 02'!$E$30:$E$112,0),'00 ACC DETAILS 02'!$A$30:$A$112,'00 ACC DETAILS 02'!$D$30:$D$112)),0) | B21: 76-W | C21: =C19 | D21: =A21*C21 | E21: =E22+12 | F21: =D21*E21/100 | G21: =D21+F21
A22: =IFERROR((LOOKUP(MATCH(B22,'00 ACC DETAILS 02'!$E$30:$E$112,0),'00 ACC DETAILS 02'!$A$30:$A$112,'00 ACC DETAILS 02'!$D$30:$D$112)),0) | B22: 77-D | C22: =C20 | D22: =A22*C22 | E22: =E24+12 | F22: =D22*E22/100 | G22: =D22+F22
A23: =IFERROR((LOOKUP(MATCH(B23,'00 ACC DETAILS 02'!$E$30:$E$112,0),'00 ACC DETAILS 02'!$A$30:$A$112,'00 ACC DETAILS 02'!$D$30:$D$112)),0) | B23: 77-W | C23: =C21 | D23: =A23*C23 | E23: =E24+12 | F23: =D23*E23/100 | G23: =D23+F23
A24: =IFERROR((LOOKUP(MATCH(B24,'00 ACC DETAILS 02'!$E$30:$E$112,0),'00 ACC DETAILS 02'!$A$30:$A$112,'00 ACC DETAILS 02'!$D$30:$D$112)),0) | B24: 78-D | C24: =C22 | D24: =A24*C24 | E24: =E26+6 | F24: =D24*E24/100 | G24: =D24+F24
A25: =IFERROR((LOOKUP(MATCH(B25,'00 ACC DETAILS 02'!$E$30:$E$112,0),'00 ACC DETAILS 02'!$A$30:$A$112,'00 ACC DETAILS 02'!$D$30:$D$112)),0) | B25: 78-W | C25: =C23 | D25: =A25*C25 | E25: =E26+6 | F25: =D25*E25/100 | G25: =D25+F25
A26: =IFERROR((LOOKUP(MATCH(B26,'00 ACC DETAILS 02'!$E$30:$E$112,0),'00 ACC DETAILS 02'!$A$30:$A$112,'00 ACC DETAILS 02'!$D$30:$D$112)),0) | B26: 79-D | C26: =C24 | D26: =A26*C26 | E26: =E27+6 | F26: =D26*E26/100 | G26: =D26+F26
A27: =IFERROR((LOOKUP(MATCH(B27,'00 ACC DETAILS 02'!$E$30:$E$112,0),'00 ACC DETAILS 02'!$A$30:$A$112,'00 ACC DETAILS 02'!$D$30:$D$112)),0) | B27: 79-W | C27: =C25 | D27: =A27*C27 | E27: =E28+6 | F27: =D27*E27/100 | G27: =D27+F27
A28: =IFERROR((LOOKUP(MATCH(B28,'00 ACC DETAILS 02'!$E$30:$E$112,0),'00 ACC DETAILS 02'!$A$30:$A$112,'00 ACC DETAILS 02'!$D$30:$D$112)),0) | B28: 80-D | C28: =C26 | D28: =A28*C28 | E28: =E29+6 | F28: =D28*E28/100 | G28: =D28+F28
A29: =IFERROR((LOOKUP(MATCH(B29,'00 ACC DETAILS 02'!$E$30:$E$112,0),'00 ACC DETAILS 02'!$A$30:$A$112,'00 ACC DETAILS 02'!$D$30:$D$112)),0) | B29: 80-W | C29: =C27 | D29: =A29*C29 | E29: =E30+6 | F29: =D29*E29/100 | G29: =D29+F29
A30: =IFERROR((LOOKUP(MATCH(B30,'00 ACC DETAILS 02'!$E$30:$E$112,0),'00 ACC DETAILS 02'!$A$30:$A$112,'00 ACC DETAILS 02'!$D$30:$D$112)),0) | B30: 81-D | C30: =C28 | D30: =A30*C30 | E30: =E31+6 | F30: =D30*E30/100 | G30: =D30+F30
A31: =IFERROR((LOOKUP(MATCH(B31,'00 ACC DETAILS 02'!$E$30:$E$112,0),'00 ACC DETAILS 02'!$A$30:$A$112,'00 ACC DETAILS 02'!$D$30:$D$112)),0) | B31: 81-W | C31: =C29 | D31: =A31*C31 | E31: =E32+6 | F31: =D31*E31/100 | G31: =D31+F31
A32: =IFERROR((LOOKUP(MATCH(B32,'00 ACC DETAILS 02'!$E$30:$E$112,0),'00 ACC DETAILS 02'!$A$30:$A$112,'00 ACC DETAILS 02'!$D$30:$D$112)),0) | B32: 82-D | C32: =C30 | D32: =A32*C32 | E32: =E33+6 | F32: =D32*E32/100 | G32: =D32+F32
A33: =IFERROR((LOOKUP(MATCH(B33,'00 ACC DETAILS 02'!$E$30:$E$112,0),'00 ACC DETAILS 02'!$A$30:$A$112,'00 ACC DETAILS 02'!$D$30:$D$112)),0) | B33: 82-W | C33: =C31 | D33: =A33*C33 | E33: =E34+6 | F33: =D33*E33/100 | G33: =D33+F33
A34: =IFERROR((LOOKUP(MATCH(B34,'00 ACC DETAILS 02'!$E$30:$E$112,0),'00 ACC DETAILS 02'!$A$30:$A$112,'00 ACC DETAILS 02'!$D$30:$D$112)),0) | B34: 83-D | C34: =C32 | D34: =A34*C34 | E34: =E35+6 | F34: =D34*E34/100 | G34: =D34+F34
A35: =IFERROR((LOOKUP(MATCH(B35,'00 ACC DETAILS 02'!$E$30:$E$112,0),'00 ACC DETAILS 02'!$A$30:$A$112,'00 ACC DETAILS 02'!$D$30:$D$112)),0) | B35: 83-W | C35: =C33 | D35: =A35*C35 | E35: =E36+6 | F35: =D35*E35/100 | G35: =D35+F35
A36: =IFERROR((LOOKUP(MATCH(B36,'00 ACC DETAILS 02'!$E$30:$E$112,0),'00 ACC DETAILS 02'!$A$30:$A$112,'00 ACC DETAILS 02'!$D$30:$D$112)),0) | B36: 84-D | C36: =C34 | D36: =A36*C36 | E36: =E37+6 | F36: =D36*E36/100 | G36: =D36+F36
... A63: =IFERROR((LOOKUP(MATCH(B63,'00 ACC DETAILS 02'!$E$30:$E$112,0),'00 ACC DETAILS 02'!$A$30:$A$112,'00 ACC DETAILS 02'!$D$30:$D$112)),0) | B63: 97-W | C63: =C61 | D63: =A63*C63 | E63: =E64+6 | F63: =D63*E63/100 | G63: =D63+F63
A64: =IFERROR((LOOKUP(MATCH(B64,'00 ACC DETAILS 02'!$E$30:$E$112,0),'00 ACC DETAILS 02'!$A$30:$A$112,'00 ACC DETAILS 02'!$D$30:$D$112)),0) | B64: 98-D | C64: 0 | D64: =A64*C64 | E64: =E65+6 | F64: =D64*E64/100 | G64: =D64+F64
A65: =IFERROR((LOOKUP(MATCH(B65,'00 ACC DETAILS 02'!$E$30:$E$112,0),'00 ACC DETAILS 02'!$A$30:$A$112,'00 ACC DETAILS 02'!$D$30:$D$112)),0) | B65: 98-W | C65: 400 | D65: =A65*C65 | E65: =E66+6 | F65: =D65*E65/100 | G65: =D65+F65
A66: =IFERROR((LOOKUP(MATCH(B66,'00 ACC DETAILS 02'!$E$30:$E$112,0),'00 ACC DETAILS 02'!$A$30:$A$112,'00 ACC DETAILS 02'!$D$30:$D$112)),0) | B66: 99-D | C66: 600 | D66: =A66*C66 | E66: =E67+6 | F66: =D66*E66/100 | G66: =D66+F66
A67: =IFERROR((LOOKUP(MATCH(B67,'00 ACC DETAILS 02'!$E$30:$E$112,0),'00 ACC DETAILS 02'!$A$30:$A$112,'00 ACC DETAILS 02'!$D$30:$D$112)),0) | B67: 99-W | C67: 450 | D67: =A67*C67 | E67: =E68+6 | F67: =D67*E67/100 | G67: =D67+F67
A68: =IFERROR((LOOKUP(MATCH(B68,'00 ACC DETAILS 02'!$E$30:$E$112,0),'00 ACC DETAILS 02'!$A$30:$A$112,'00 ACC DETAILS 02'!$D$30:$D$112)),0) | B68: 2000-D | C68: 750 | D68: =A68*C68 | E68: =E69+6 | F68: =D68*E68/100 | G68: =D68+F68
A69: =IFERROR((LOOKUP(MATCH(B69,'00 ACC DETAILS 02'!$E$30:$E$112,0),'00 ACC DETAILS 02'!$A$30:$A$112,'00 ACC DETAILS 02'!$D$30:$D$112)),0) | B69: 2000-W | C69: =C67 | D69: =A69*C69 | E69: =E70+6 | F69: =D69*E69/100 | G69: =D69+F69
A70: =IFERROR((LOOKUP(MATCH(B70,'00 ACC DETAILS 02'!$E$30:$E$112,0),'00 ACC DETAILS 02'!$A$30:$A$112,'00 ACC DETAILS 02'!$D$30:$D$112)),0) | B70: 2001-D | C70: =C68 | D70: =A70*C70 | E70: =E71+6 | F70: =D70*E70/100 | G70: =D70+F70
A71: =IFERROR((LOOKUP(MATCH(B71,'00 ACC DETAILS 02'!$E$30:$E$112,0),'00 ACC DETAILS 02'!$A$30:$A$112,'00 ACC DETAILS 02'!$D$30:$D$112)),0) | B71: 2001-W | C71: =C63 | D71: =A71*C71 | E71: =E72+6 | F71: =D71*E71/100 | G71: =D71+F71
A72: =IFERROR((LOOKUP(MATCH(B72,'00 ACC DETAILS 02'!$E$30:$E$112,0),'00 ACC DETAILS 02'!$A$30:$A$112,'00 ACC DETAILS 02'!$D$30:$D$112)),0) | B72: 2002-D | C72: =C62 | D72: =A72*C72 | E72: =E73+6 | F72: =D72*E72/100 | G72: =D72+F72
A73: =IFERROR((LOOKUP(MATCH(B73,'00 ACC DETAILS 02'!$E$30:$E$112,0),'00 ACC DETAILS 02'!$A$30:$A$112,'00 ACC DETAILS 02'!$D$30:$D$112)),0) | B73: 2002-W | C73: =C71 | D73: =A73*C73 | E73: =E74+6 | F73: =D73*E73/100 | G73: =D73+F73
A74: =IFERROR((LOOKUP(MATCH(B74,'00 ACC DETAILS 02'!$E$30:$E$112,0),'00 ACC DETAILS 02'!$A$30:$A$112,'00 ACC DETAILS 02'!$D$30:$D$112)),0) | B74: 2003-D | C74: =C72 | D74: =A74*C74 | E74: =E75+6 | F74: =D74*E74/100 | G74: =D74+F74
A75: =IFERROR((LOOKUP(MATCH(B75,'00 ACC DETAILS 02'!$E$30:$E$112,0),'00 ACC DETAILS 02'!$A$30:$A$112,'00 ACC DETAILS 02'!$D$30:$D$112)),0) | B75: 2003-W | C75: =C73 | D75: =A75*C75 | E75: =E76+6 | F75: =D75*E75/100 | G75: =D75+F75
A76: =IFERROR((LOOKUP(MATCH(B76,'00 ACC DETAILS 02'!$E$30:$E$112,0),'00 ACC DETAILS 02'!$A$30:$A$112,'00 ACC DETAILS 02'!$D$30:$D$112)),0) | B76: 2004-D | C76: =C74 | D76: =A76*C76 | E76: =E77+6 | F76: =D76*E76/100 | G76: =D76+F76
A77: =IFERROR((LOOKUP(MATCH(B77,'00 ACC DETAILS 02'!$E$30:$E$112,0),'00 ACC DETAILS 02'!$A$30:$A$112,'00 ACC DETAILS 02'!$D$30:$D$112)),0) | B77: 2004-W | C77: =C75 | D77: =A77*C77 | E77: =E78+6 | F77: =D77*E77/100 | G77: =D77+F77
A78: =IFERROR((LOOKUP(MATCH(B78,'00 ACC DETAILS 02'!$E$30:$E$112,0),'00 ACC DETAILS 02'!$A$30:$A$112,'00 ACC DETAILS 02'!$D$30:$D$112)),0) | B78: 2005-D | C78: =C76 | D78: =A78*C78 | E78: =E79+6 | F78: =D78*E78/100 | G78: =D78+F78
A79: =IFERROR((LOOKUP(MATCH(B79,'00 ACC DETAILS 02'!$E$30:$E$112,0),'00 ACC DETAILS 02'!$A$30:$A$112,'00 ACC DETAILS 02'!$D$30:$D$112)),0) | B79: 2005-W | C79: =C77 | D79: =A79*C79 | E79: =E80+6 | F79: =D79*E79/100 | G79: =D79+F79
A80: =IFERROR((LOOKUP(MATCH(B80,'00 ACC DETAILS 02'!$E$30:$E$112,0),'00 ACC DETAILS 02'!$A$30:$A$112,'00 ACC DETAILS 02'!$D$30:$D$112)),0) | B80: 2006-D | C80: =C78 | D80: =A80*C80 | E80: =E81+6 | F80: =D80*E80/100 | G80: =D80+F80
A81: =IFERROR((LOOKUP(MATCH(B81,'00 ACC DETAILS 02'!$E$30:$E$112,0),'00 ACC DETAILS 02'!$A$30:$A$112,'00 ACC DETAILS 02'!$D$30:$D$112)),0) | B81: 2006-W | C81: =C79 | D81: =A81*C81 | E81: =E82+6 | F81: =D81*E81/100 | G81: =D81+F81
A82: =IFERROR((LOOKUP(MATCH(B82,'00 ACC DETAILS 02'!$E$30:$E$112,0),'00 ACC DETAILS 02'!$A$30:$A$112,'00 ACC DETAILS 02'!$D$30:$D$112)),0) | B82: 2007-D | C82: =C80 | D82: =A82*C82 | E82: =E83+6 | F82: =D82*E82/100 | G82: =D82+F82
A83: =IFERROR((LOOKUP(MATCH(B83,'00 ACC DETAILS 02'!$E$30:$E$112,0),'00 ACC DETAILS 02'!$A$30:$A$112,'00 ACC DETAILS 02'!$D$30:$D$112)),0) | B83: 2007-W | C83: =C81 | D83: =A83*C83 | E83: =E84+6 | F83: =D83*E83/100 | G83: =D83+F83
A84: =IFERROR((LOOKUP(MATCH(B84,'00 ACC DETAILS 02'!$E$30:$E$112,0),'00 ACC DETAILS 02'!$A$30:$A$112,'00 ACC DETAILS 02'!$D$30:$D$112)),0) | B84: 2008-D | C84: =C82 | D84: =A84*C84 | E84: =E85+6 | F84: =D84*E84/100 | G84: =D84+F84
A85: =IFERROR((LOOKUP(MATCH(B85,'00 ACC DETAILS 02'!$E$30:$E$112,0),'00 ACC DETAILS 02'!$A$30:$A$112,'00 ACC DETAILS 02'!$D$30:$D$112)),0) | B85: 2008-W | C85: =C83 | D85: =A85*C85 | E85: =E86+6 | F85: =D85*E85/100 | G85: =D85+F85
A86: =IFERROR((LOOKUP(MATCH(B86,'00 ACC DETAILS 02'!$E$30:$E$112,0),'00 ACC DETAILS 02'!$A$30:$A$112,'00 ACC DETAILS 02'!$D$30:$D$112)),0) | B86: 2009-D | C86: 2250 | D86: =A86*C86 | E86: =E87+6 | F86: =D86*E86/100 | G86: =D86+F86
A87: =IFERROR((LOOKUP(MATCH(B87,'00 ACC DETAILS 02'!$E$30:$E$112,0),'00 ACC DETAILS 02'!$A$30:$A$112,'00 ACC DETAILS 02'!$D$30:$D$112)),0) | B87: 2009-W | C87: =C85 | D87: =A87*C87 | E87: =E88+6 | F87: =D87*E87/100 | G87: =D87+F87
A88: =IFERROR((LOOKUP(MATCH(B88,'00 ACC DETAILS 02'!$E$30:$E$112,0),'00 ACC DETAILS 02'!$A$30:$A$112,'00 ACC DETAILS 02'!$D$30:$D$112)),0) | B88: 2010-D | C88: =C86 | D88: =A88*C88 | E88: =E89+6 | F88: =D88*E88/100 | G88: =D88+F88
A89: =IFERROR((LOOKUP(MATCH(B89,'00 ACC DETAILS 02'!$E$30:$E$112,0),'00 ACC DETAILS 02'!$A$30:$A$112,'00 ACC DETAILS 02'!$D$30:$D$112)),0) | B89: 2010-W | C89: =C87 | D89: =A89*C89 | E89: =E90+6 | F89: =D89*E89/100 | G89: =D89+F89
A90: =IFERROR((LOOKUP(MATCH(B90,'00 ACC DETAILS 02'!$E$30:$E$112,0),'00 ACC DETAILS 02'!$A$30:$A$112,'00 ACC DETAILS 02'!$D$30:$D$112)),0) | B90: 2011-D | C90: =C88 | D90: =A90*C90 | E90: =E91+6 | F90: =D90*E90/100 | G90: =D90+F90
A91: =IFERROR((LOOKUP(MATCH(B91,'00 ACC DETAILS 02'!$E$30:$E$112,0),'00 ACC DETAILS 02'!$A$30:$A$112,'00 ACC DETAILS 02'!$D$30:$D$112)),0) | B91: 2011-W | C91: =C89 | D91: =A91*C91 | E91: =E92+6 | F91: =D91*E91/100 | G91: =D91+F91
A92: =IFERROR((LOOKUP(MATCH(B92,'00 ACC DETAILS 02'!$E$30:$E$112,0),'00 ACC DETAILS 02'!$A$30:$A$112,'00 ACC DETAILS 02'!$D$30:$D$112)),0) | B92: 2012-D | C92: 2550 | D92: =A92*C92 | E92: =E93+6 | F92: =D92*E92/100 | G92: =D92+F92
A93: =IFERROR((LOOKUP(MATCH(B93,'00 ACC DETAILS 02'!$E$30:$E$112,0),'00 ACC DETAILS 02'!$A$30:$A$112,'00 ACC DETAILS 02'!$D$30:$D$112)),0) | B93: 2012-W | C93: 1700 | D93: =A93*C93 | E93: =E94+6 | F93: =D93*E93/100 | G93: =D93+F93
A94: =IFERROR((LOOKUP(MATCH(B94,'00 ACC DETAILS 02'!$E$30:$E$112,0),'00 ACC DETAILS 02'!$A$30:$A$112,'00 ACC DETAILS 02'!$D$30:$D$112)),0) | B94: 2013-D | C94: =17*150 | D94: =A94*C94 | E94: =E95+6 | F94: =D94*E94/100 | G94: =D94+F94
A95: =IFERROR((LOOKUP(MATCH(B95,'00 ACC DETAILS 02'!$E$30:$E$112,0),'00 ACC DETAILS 02'!$A$30:$A$112,'00 ACC DETAILS 02'!$D$30:$D$112)),0) | B95: 2013-W | C95: =17*100 | D95: =A95*C95 | E95: =E96+6 | F95: =D95*E95/100 | G95: =D95+F95
A96: =IFERROR((LOOKUP(MATCH(B96,'00 ACC DETAILS 02'!$E$30:$E$112,0),'00 ACC DETAILS 02'!$A$30:$A$112,'00 ACC DETAILS 02'!$D$30:$D$112)),0) | B96: 2014-D | C96: =C94 | D96: =A96*C96 | E96: =E97+6 | F96: =D96*E96/100 | G96: =D96+F96
A97: =IFERROR((LOOKUP(MATCH(B97,'00 ACC DETAILS 02'!$E$30:$E$112,0),'00 ACC DETAILS 02'!$A$30:$A$112,'00 ACC DETAILS 02'!$D$30:$D$112)),0) | B97: 2014-W | C97: =17*100 | D97: =A97*C97 | E97: =E98+6 | F97: =D97*E97/100 | G97: =D97+F97
A98: =IFERROR((LOOKUP(MATCH(B98,'00 ACC DETAILS 02'!$E$30:$E$112,0),'00 ACC DETAILS 02'!$A$30:$A$112,'00 ACC DETAILS 02'!$D$30:$D$112)),0) | B98: 2015-D | C98: =C96 | D98: =A98*C98 | E98: =E99+6 | F98: =D98*E98/100 | G98: =D98+F98
A99: =IFERROR((LOOKUP(MATCH(B99,'00 ACC DETAILS 02'!$E$30:$E$112,0),'00 ACC DETAILS 02'!$A$30:$A$112,'00 ACC DETAILS 02'!$D$30:$D$112)),0) | B99: 2015-W | C99: =17*100 | D99: =A99*C99 | E99: =E100+6 | F99: =D99*E99/100 | G99: =D99+F99
A100: =IFERROR((LOOKUP(MATCH(B100,'00 ACC DETAILS 02'!$E$30:$E$112,0),'00 ACC DETAILS 02'!$A$30:$A$112,'00 ACC DETAILS 02'!$D$30:$D$112)),0) | B100: 2016-D | C100: =C98 | D100: =A100*C100 | E100: =E101+6 | F100: =D100*E100/100 | G100: =D100+F100
A101: =IFERROR((LOOKUP(MATCH(B101,'00 ACC DETAILS 02'!$E$30:$E$112,0),'00 ACC DETAILS 02'!$A$30:$A$112,'00 ACC DETAILS 02'!$D$30:$D$112)),0) | B101: 2016-W | C101: =17*100 | D101: =A101*C101 | E101: 11 | F101: =D101*E101/100 | G101: =D101+F101
A102: Sub-total | D102: =SUM(D19:D101) | F102: =SUM(F19:F101) | G102: =SUM(G19:G101)
A103: Add old accounts: Prior to July 1,1975 | G103: 0
A104: TOTAL | G104: =G102+G103
A105: Note: If you have any problem with your account and our services, please feel free to see us in our office.
A107: Prepared by: | C107: Checked by: | D107: Recommending Approval: | G107: Approved:
A109: CATHERINE DC. AUSTRIA | C109: MAGNOLIA L. TAYAO | E109: JUANITO C. VALONES | G109: ROBERTO J. DELA CRUZ
A110: Accounting Proc. A | C110: Head, Billing Unit | E110: O&M Chief | G110: Manager, BANE IMO
A119: Republika ng Pilipinas
A120: National Irrigation Administration
A121: (Pambansang Pangasiwaan ng Patubig)
A122: Bulacan – Aurora – Nueva Ecija Irrigation Management Office
A123: Tambubong, San Rafael, Bulacan
A125: Office Address : Tambubong, San Rafael, Bulacan | G125: Telefax No. (044) 766-3888
A126: Telephone Nos. : (044) 766-3888 | G126: TIN No. 000-578-009-000
A127: Email Address : niabaneimoafs@yahoo.com
A129: STATEMENT OF ACCOUNT
A130: =A12
A132: FARMER CODE NO.: | C132: =C14 | F132: WRFT Div. : | G132: =G14
A133: Lot No.: | C133: =C15 | F133: Area:. | G133: =G15
A134: Name of Landowner: | E134: Address:
A135: Name of Farmers: | C135: =C17 | E135: Address:
A136: Area | B136: C. S. | C136: Rate | D136: Principal | E136: %Penalty | F136: Penalty(Cash) | G136: Total
A137: =A19 | B137: 75-W | C137: =1.1*100 | D137: =A137*C137 | F137: =D137*E137/100 | G137: =D137+F137
A138: =A20 | B138: 76-D | C138: =1.1*150 | D138: =A138*C138 | F138: =D138*E138/100 | G138: =D138+F138
A139: =A21 | B139: 76-W | C139: =1.1*100 | D139: =A139*C139 | F139: =D139*E139/100 | G139: =D139+F139
A140: =A22 | B140: 77-D | C140: =1.1*150 | D140: =A140*C140 | F140: =D140*E140/100 | G140: =D140+F140
A141: =A23 | B141: 77-W | C141: =1.1*100 | D141: =A141*C141 | F141: =D141*E141/100 | G141: =D141+F141
A142: =A24 | B142: 78-D | C142: =1.1*150 | D142: =A142*C142 | F142: =D142*E142/100 | G142: =D142+F142
A143: =A25 | B143: 78-W | C143: =1.1*100 | D143: =A143*C143 | F143: =D143*E143/100 | G143: =D143+F143
A144: =A26 | B144: 79-D | C144: =1.1*150 | D144: =A144*C144 | F144: =D144*E144/100 | G144: =D144+F144
A145: =A27 | B145: 79-W | C145: =1.3*100 | D145: =A145*C145 | F145: =D145*E145/100 | G145: =D145+F145
A146: =A28 | B146: 80-D | C146: =1.3*150 | D146: =A146*C146 | F146: =D146*E146/100 | G146: =D146+F146
A147: =A29 | B147: 80-W | C147: =1.3*100 | D147: =A147*C147 | F147: =D147*E147/100 | G147: =D147+F147
A148: =A30 | B148: 81-D | C148: =1.4*150 | D148: =A148*C148 | F148: =D148*E148/100 | G148: =D148+F148
A149: =A31 | B149: 81-W | C149: =1.45*100 | D149: =A149*C149 | F149: =D149*E149/100 | G149: =D149+F149
A150: =A32 | B150: 82-D | C150: =1.55*150 | D150: =A150*C150 | F150: =D150*E150/100 | G150: =D150+F150
...

Sheet 00 ACC DETAILS 03
B2: ACCOUNT DETAILS
B3: Lot No. | C3: 3809
B4: Division | C4: ='00 ACC DETAILS 01'!C4
B5: Name of IA | C5: ='00 ACC DETAILS 01'!C5
B6: Name of Land Owner
B7: First Name | C7: ='00 ACC DETAILS 01'!C7
B8: Middle Name | C8: ='00 ACC DETAILS 01'!C8
B9: Surname | C9: ='00 ACC DETAILS 01'!C9
B10: Name of Farmer/Land Tiller
B11: First Name | C11: MARCELO
B12: Middle Name
B13: Surname | C13: GUINTO
B14: Location of Lot
B15: Baranggay | C15: ='00 ACC DETAILS 01'!C15
B16: Municipality/City | C16: ='00 ACC DETAILS 01'!C16
B17: Province | C17: ='00 ACC DETAILS 01'!C17
B18: Address of Land Owner
B19: Baranggay | C19: ='00 ACC DETAILS 01'!C19
B20: Municipality/City | C20: ='00 ACC DETAILS 01'!C20
B21: Province | C21: ='00 ACC DETAILS 01'!C21
B22: Address of Farmer/Land Tiller
B23: Baranggay | C23: ='00 ACC DETAILS 01'!C23
B24: Municipality/City | C24: ='00 ACC DETAILS 01'!C24
B25: Province | C25: ='00 ACC DETAILS 01'!C25
A28: IRRIGATION FEE REGISTRY (IFR)
B29: Wet/Dry | C29: Year | D29: Area
A30: 1 | E30: =IF(ISBLANK(B30),0,IF(C30<2000,RIGHT(C30,2),C30)&"-"&IF(B30="wet","W","D"))
A31: 2 | E31: =IF(ISBLANK(B31),0,IF(C31<2000,RIGHT(C31,2),C31)&"-"&IF(B31="wet","W","D"))
A32: 3 | E32: =IF(ISBLANK(B32),0,IF(C32<2000,RIGHT(C32,2),C32)&"-"&IF(B32="wet","W","D"))
A33: 4 | E33: =IF(ISBLANK(B33),0,IF(C33<2000,RIGHT(C33,2),C33)&"-"&IF(B33="wet","W","D"))
A34: 5 | E34: =IF(ISBLANK(B34),0,IF(C34<2000,RIGHT(C34,2),C34)&"-"&IF(B34="wet","W","D"))
A35: 6 | E35: =IF(ISBLANK(B35),0,IF(C35<2000,RIGHT(C35,2),C35)&"-"&IF(B35="wet","W","D"))
A36: 7 | E36: =IF(ISBLANK(B36),0,IF(C36<2000,RIGHT(C36,2),C36)&"-"&IF(B36="wet","W","D"))
A37: 8 | E37: =IF(ISBLANK(B37),0,IF(C37<2000,RIGHT(C37,2),C37)&"-"&IF(B37="wet","W","D"))
A38: 9 | E38: =IF(ISBLANK(B38),0,IF(C38<2000,RIGHT(C38,2),C38)&"-"&IF(B38="wet","W","D"))
A39: 10 | E39: =IF(ISBLANK(B39),0,IF(C39<2000,RIGHT(C39,2),C39)&"-"&IF(B39="wet","W","D"))
A40: 11 | E40: =IF(ISBLANK(B40),0,IF(C40<2000,RIGHT(C40,2),C40)&"-"&IF(B40="wet","W","D"))
A41: 12 | E41: =IF(ISBLANK(B41),0,IF(C41<2000,RIGHT(C41,2),C41)&"-"&IF(B41="wet","W","D"))
... A112: 83 | E112: =IF(ISBLANK(B112),0,IF(C112<2000,RIGHT(C112,2),C112)&"-"&IF(B112="wet","W","D"))

Sheet 01 SOA 03
A11: STATEMENT OF ACCOUNT
A12: ="as of "&TEXT(TODAY(),"mmmm dd, yyyy")
A14: FARMER CODE NO.: | F14: WRFT Div. : | G14: ='00 ACC DETAILS 03'!C4&" - "&'00 ACC DETAILS 03'!C5
A15: Lot No.: | C15: ='00 ACC DETAILS 03'!C3 | F15: Area:. | G15: {=IFERROR(0,LOOKUP(2,1/(A19:A101),A19:A101))}
A16: Name of Landowner: | C16: =IF(ISBLANK('00 ACC DETAILS 01'!C8),'00 ACC DETAILS 01'!C7&" "&'00 ACC DETAILS 01'!C9,'00 ACC DETAILS 01'!C7&" "&'00 ACC DETAILS 01'!C8&" "&'00 ACC DETAILS 01'!C9) | E16: Address:
A17: Name of Farmers: | C17: =IF(ISBLANK('00 ACC DETAILS 03'!C12),'00 ACC DETAILS 03'!C11&" "&'00 ACC DETAILS 03'!C13,'00 ACC DETAILS 03'!C11&" "&'00 ACC DETAILS 03'!C12&" "&'00 ACC DETAILS 03'!C13) | E17: Address:
A18: Area | B18: C. S. | C18: Rate | D18: Principal | E18: %Penalty | F18: Penalty(Cash) | G18: Total
A19: =IFERROR((LOOKUP(MATCH(B19,'00 ACC DETAILS 03'!$E$30:$E$112,0),'00 ACC DETAILS 03'!$A$30:$A$112,'00 ACC DETAILS 03'!$D$30:$D$112)),0) | B19: 75-W | C19: =15*100 | D19: =A19*C19 | E19: =E21+12 | F19: =D19*E19/100 | G19: =D19+F19
A20: =IFERROR((LOOKUP(MATCH(B20,'00 ACC DETAILS 03'!$E$30:$E$112,0),'00 ACC DETAILS 03'!$A$30:$A$112,'00 ACC DETAILS 03'!$D$30:$D$112)),0) | B20: 76-D | C20: =15*150 | D20: =A20*C20 | E20: =E22+12 | F20: =D20*E20/100 | G20: =D20+F20
A21: =IFERROR((LOOKUP(MATCH(B21,'00 ACC DETAILS 03'!$E$30:$E$112,0),'00 ACC DETAILS 03'!$A$30:$A$112,'00 ACC DETAILS 03'!$D$30:$D$112)),0) | B21: 76-W | C21: =C19 | D21: =A21*C21 | E21: =E22+12 | F21: =D21*E21/100 | G21: =D21+F21
A22: =IFERROR((LOOKUP(MATCH(B22,'00 ACC DETAILS 03'!$E$30:$E$112,0),'00 ACC DETAILS 03'!$A$30:$A$112,'00 ACC DETAILS 03'!$D$30:$D$112)),0) | B22: 77-D | C22: =C20 | D22: =A22*C22 | E22: =E24+12 | F22: =D22*E22/100 | G22: =D22+F22
A23: =IFERROR((LOOKUP(MATCH(B23,'00 ACC DETAILS 03'!$E$30:$E$112,0),'00 ACC DETAILS 03'!$A$30:$A$112,'00 ACC DETAILS 03'!$D$30:$D$112)),0) | B23: 77-W | C23: =C21 | D23: =A23*C23 | E23: =E24+12 | F23: =D23*E23/100 | G23: =D23+F23
A24: =IFERROR((LOOKUP(MATCH(B24,'00 ACC DETAILS 03'!$E$30:$E$112,0),'00 ACC DETAILS 03'!$A$30:$A$112,'00 ACC DETAILS 03'!$D$30:$D$112)),0) | B24: 78-D | C24: =C22 | D24: =A24*C24 | E24: =E26+6 | F24: =D24*E24/100 | G24: =D24+F24
A25: =IFERROR((LOOKUP(MATCH(B25,'00 ACC DETAILS 03'!$E$30:$E$112,0),'00 ACC DETAILS 03'!$A$30:$A$112,'00 ACC DETAILS 03'!$D$30:$D$112)),0) | B25: 78-W | C25: =C23 | D25: =A25*C25 | E25: =E26+6 | F25: =D25*E25/100 | G25: =D25+F25
A26: =IFERROR((LOOKUP(MATCH(B26,'00 ACC DETAILS 03'!$E$30:$E$112,0),'00 ACC DETAILS 03'!$A$30:$A$112,'00 ACC DETAILS 03'!$D$30:$D$112)),0) | B26: 79-D | C26: =C24 | D26: =A26*C26 | E26: =E27+6 | F26: =D26*E26/100 | G26: =D26+F26
A27: =IFERROR((LOOKUP(MATCH(B27,'00 ACC DETAILS 03'!$E$30:$E$112,0),'00 ACC DETAILS 03'!$A$30:$A$112,'00 ACC DETAILS 03'!$D$30:$D$112)),0) | B27: 79-W | C27: =C25 | D27: =A27*C27 | E27: =E28+6 | F27: =D27*E27/100 | G27: =D27+F27
A28: =IFERROR((LOOKUP(MATCH(B28,'00 ACC DETAILS 03'!$E$30:$E$112,0),'00 ACC DETAILS 03'!$A$30:$A$112,'00 ACC DETAILS 03'!$D$30:$D$112)),0) | B28: 80-D | C28: =C26 | D28: =A28*C28 | E28: =E29+6 | F28: =D28*E28/100 | G28: =D28+F28
A29: =IFERROR((LOOKUP(MATCH(B29,'00 ACC DETAILS 03'!$E$30:$E$112,0),'00 ACC DETAILS 03'!$A$30:$A$112,'00 ACC DETAILS 03'!$D$30:$D$112)),0) | B29: 80-W | C29: =C27 | D29: =A29*C29 | E29: =E30+6 | F29: =D29*E29/100 | G29: =D29+F29
A30: =IFERROR((LOOKUP(MATCH(B30,'00 ACC DETAILS 03'!$E$30:$E$112,0),'00 ACC DETAILS 03'!$A$30:$A$112,'00 ACC DETAILS 03'!$D$30:$D$112)),0) | B30: 81-D | C30: =C28 | D30: =A30*C30 | E30: =E31+6 | F30: =D30*E30/100 | G30: =D30+F30
A31: =IFERROR((LOOKUP(MATCH(B31,'00 ACC DETAILS 03'!$E$30:$E$112,0),'00 ACC DETAILS 03'!$A$30:$A$112,'00 ACC DETAILS 03'!$D$30:$D$112)),0) | B31: 81-W | C31: =C29 | D31: =A31*C31 | E31: =E32+6 | F31: =D31*E31/100 | G31: =D31+F31
A32: =IFERROR((LOOKUP(MATCH(B32,'00 ACC DETAILS 03'!$E$30:$E$112,0),'00 ACC DETAILS 03'!$A$30:$A$112,'00 ACC DETAILS 03'!$D$30:$D$112)),0) | B32: 82-D | C32: =C30 | D32: =A32*C32 | E32: =E33+6 | F32: =D32*E32/100 | G32: =D32+F32
A33: =IFERROR((LOOKUP(MATCH(B33,'00 ACC DETAILS 03'!$E$30:$E$112,0),'00 ACC DETAILS 03'!$A$30:$A$112,'00 ACC DETAILS 03'!$D$30:$D$112)),0) | B33: 82-W | C33: =C31 | D33: =A33*C33 | E33: =E34+6 | F33: =D33*E33/100 | G33: =D33+F33
A34: =IFERROR((LOOKUP(MATCH(B34,'00 ACC DETAILS 03'!$E$30:$E$112,0),'00 ACC DETAILS 03'!$A$30:$A$112,'00 ACC DETAILS 03'!$D$30:$D$112)),0) | B34: 83-D | C34: =C32 | D34: =A34*C34 | E34: =E35+6 | F34: =D34*E34/100 | G34: =D34+F34
A35: =IFERROR((LOOKUP(MATCH(B35,'00 ACC DETAILS 03'!$E$30:$E$112,0),'00 ACC DETAILS 03'!$A$30:$A$112,'00 ACC DETAILS 03'!$D$30:$D$112)),0) | B35: 83-W | C35: =C33 | D35: =A35*C35 | E35: =E36+6 | F35: =D35*E35/100 | G35: =D35+F35
A36: =IFERROR((LOOKUP(MATCH(B36,'00 ACC DETAILS 03'!$E$30:$E$112,0),'00 ACC DETAILS 03'!$A$30:$A$112,'00 ACC DETAILS 03'!$D$30:$D$112)),0) | B36: 84-D | C36: =C34 | D36: =A36*C36 | E36: =E37+6 | F36: =D36*E36/100 | G36: =D36+F36
... A63: =IFERROR((LOOKUP(MATCH(B63,'00 ACC DETAILS 03'!$E$30:$E$112,0),'00 ACC DETAILS 03'!$A$30:$A$112,'00 ACC DETAILS 03'!$D$30:$D$112)),0) | B63: 97-W | C63: =C61 | D63: =A63*C63 | E63: =E64+6 | F63: =D63*E63/100 | G63: =D63+F63
A64: =IFERROR((LOOKUP(MATCH(B64,'00 ACC DETAILS 03'!$E$30:$E$112,0),'00 ACC DETAILS 03'!$A$30:$A$112,'00 ACC DETAILS 03'!$D$30:$D$112)),0) | B64: 98-D | C64: 0 | D64: =A64*C64 | E64: =E65+6 | F64: =D64*E64/100 | G64: =D64+F64
A65: =IFERROR((LOOKUP(MATCH(B65,'00 ACC DETAILS 03'!$E$30:$E$112,0),'00 ACC DETAILS 03'!$A$30:$A$112,'00 ACC DETAILS 03'!$D$30:$D$112)),0) | B65: 98-W | C65: 400 | D65: =A65*C65 | E65: =E66+6 | F65: =D65*E65/100 | G65: =D65+F65
A66: =IFERROR((LOOKUP(MATCH(B66,'00 ACC DETAILS 03'!$E$30:$E$112,0),'00 ACC DETAILS 03'!$A$30:$A$112,'00 ACC DETAILS 03'!$D$30:$D$112)),0) | B66: 99-D | C66: 600 | D66: =A66*C66 | E66: =E67+6 | F66: =D66*E66/100 | G66: =D66+F66
A67: =IFERROR((LOOKUP(MATCH(B67,'00 ACC DETAILS 03'!$E$30:$E$112,0),'00 ACC DETAILS 03'!$A$30:$A$112,'00 ACC DETAILS 03'!$D$30:$D$112)),0) | B67: 99-W | C67: 450 | D67: =A67*C67 | E67: =E68+6 | F67: =D67*E67/100 | G67: =D67+F67
A68: =IFERROR((LOOKUP(MATCH(B68,'00 ACC DETAILS 03'!$E$30:$E$112,0),'00 ACC DETAILS 03'!$A$30:$A$112,'00 ACC DETAILS 03'!$D$30:$D$112)),0) | B68: 2000-D | C68: 750 | D68: =A68*C68 | E68: =E69+6 | F68: =D68*E68/100 | G68: =D68+F68
A69: =IFERROR((LOOKUP(MATCH(B69,'00 ACC DETAILS 03'!$E$30:$E$112,0),'00 ACC DETAILS 03'!$A$30:$A$112,'00 ACC DETAILS 03'!$D$30:$D$112)),0) | B69: 2000-W | C69: =C67 | D69: =A69*C69 | E69: =E70+6 | F69: =D69*E69/100 | G69: =D69+F69
A70: =IFERROR((LOOKUP(MATCH(B70,'00 ACC DETAILS 03'!$E$30:$E$112,0),'00 ACC DETAILS 03'!$A$30:$A$112,'00 ACC DETAILS 03'!$D$30:$D$112)),0) | B70: 2001-D | C70: =C68 | D70: =A70*C70 | E70: =E71+6 | F70: =D70*E70/100 | G70: =D70+F70
A71: =IFERROR((LOOKUP(MATCH(B71,'00 ACC DETAILS 03'!$E$30:$E$112,0),'00 ACC DETAILS 03'!$A$30:$A$112,'00 ACC DETAILS 03'!$D$30:$D$112)),0) | B71: 2001-W | C71: =C63 | D71: =A71*C71 | E71: =E72+6 | F71: =D71*E71/100 | G71: =D71+F71
A72: =IFERROR((LOOKUP(MATCH(B72,'00 ACC DETAILS 03'!$E$30:$E$112,0),'00 ACC DETAILS 03'!$A$30:$A$112,'00 ACC DETAILS 03'!$D$30:$D$112)),0) | B72: 2002-D | C72: =C62 | D72: =A72*C72 | E72: =E73+6 | F72: =D72*E72/100 | G72: =D72+F72
A73: =IFERROR((LOOKUP(MATCH(B73,'00 ACC DETAILS 03'!$E$30:$E$112,0),'00 ACC DETAILS 03'!$A$30:$A$112,'00 ACC DETAILS 03'!$D$30:$D$112)),0) | B73: 2002-W | C73: =C71 | D73: =A73*C73 | E73: =E74+6 | F73: =D73*E73/100 | G73: =D73+F73
A74: =IFERROR((LOOKUP(MATCH(B74,'00 ACC DETAILS 03'!$E$30:$E$112,0),'00 ACC DETAILS 03'!$A$30:$A$112,'00 ACC DETAILS 03'!$D$30:$D$112)),0) | B74: 2003-D | C74: =C72 | D74: =A74*C74 | E74: =E75+6 | F74: =D74*E74/100 | G74: =D74+F74
A75: =IFERROR((LOOKUP(MATCH(B75,'00 ACC DETAILS 03'!$E$30:$E$112,0),'00 ACC DETAILS 03'!$A$30:$A$112,'00 ACC DETAILS 03'!$D$30:$D$112)),0) | B75: 2003-W | C75: =C73 | D75: =A75*C75 | E75: =E76+6 | F75: =D75*E75/100 | G75: =D75+F75
A76: =IFERROR((LOOKUP(MATCH(B76,'00 ACC DETAILS 03'!$E$30:$E$112,0),'00 ACC DETAILS 03'!$A$30:$A$112,'00 ACC DETAILS 03'!$D$30:$D$112)),0) | B76: 2004-D | C76: =C74 | D76: =A76*C76 | E76: =E77+6 | F76: =D76*E76/100 | G76: =D76+F76
A77: =IFERROR((LOOKUP(MATCH(B77,'00 ACC DETAILS 03'!$E$30:$E$112,0),'00 ACC DETAILS 03'!$A$30:$A$112,'00 ACC DETAILS 03'!$D$30:$D$112)),0) | B77: 2004-W | C77: =C75 | D77: =A77*C77 | E77: =E78+6 | F77: =D77*E77/100 | G77: =D77+F77
A78: =IFERROR((LOOKUP(MATCH(B78,'00 ACC DETAILS 03'!$E$30:$E$112,0),'00 ACC DETAILS 03'!$A$30:$A$112,'00 ACC DETAILS 03'!$D$30:$D$112)),0) | B78: 2005-D | C78: =C76 | D78: =A78*C78 | E78: =E79+6 | F78: =D78*E78/100 | G78: =D78+F78
A79: =IFERROR((LOOKUP(MATCH(B79,'00 ACC DETAILS 03'!$E$30:$E$112,0),'00 ACC DETAILS 03'!$A$30:$A$112,'00 ACC DETAILS 03'!$D$30:$D$112)),0) | B79: 2005-W | C79: =C77 | D79: =A79*C79 | E79: =E80+6 | F79: =D79*E79/100 | G79: =D79+F79
A80: =IFERROR((LOOKUP(MATCH(B80,'00 ACC DETAILS 03'!$E$30:$E$112,0),'00 ACC DETAILS 03'!$A$30:$A$112,'00 ACC DETAILS 03'!$D$30:$D$112)),0) | B80: 2006-D | C80: =C78 | D80: =A80*C80 | E80: =E81+6 | F80: =D80*E80/100 | G80: =D80+F80
A81: =IFERROR((LOOKUP(MATCH(B81,'00 ACC DETAILS 03'!$E$30:$E$112,0),'00 ACC DETAILS 03'!$A$30:$A$112,'00 ACC DETAILS 03'!$D$30:$D$112)),0) | B81: 2006-W | C81: =C79 | D81: =A81*C81 | E81: =E82+6 | F81: =D81*E81/100 | G81: =D81+F81
A82: =IFERROR((LOOKUP(MATCH(B82,'00 ACC DETAILS 03'!$E$30:$E$112,0),'00 ACC DETAILS 03'!$A$30:$A$112,'00 ACC DETAILS 03'!$D$30:$D$112)),0) | B82: 2007-D | C82: =C80 | D82: =A82*C82 | E82: =E83+6 | F82: =D82*E82/100 | G82: =D82+F82
A83: =IFERROR((LOOKUP(MATCH(B83,'00 ACC DETAILS 03'!$E$30:$E$112,0),'00 ACC DETAILS 03'!$A$30:$A$112,'00 ACC DETAILS 03'!$D$30:$D$112)),0) | B83: 2007-W | C83: =C81 | D83: =A83*C83 | E83: =E84+6 | F83: =D83*E83/100 | G83: =D83+F83
A84: =IFERROR((LOOKUP(MATCH(B84,'00 ACC DETAILS 03'!$E$30:$E$112,0),'00 ACC DETAILS 03'!$A$30:$A$112,'00 ACC DETAILS 03'!$D$30:$D$112)),0) | B84: 2008-D | C84: =C82 | D84: =A84*C84 | E84: =E85+6 | F84: =D84*E84/100 | G84: =D84+F84
A85: =IFERROR((LOOKUP(MATCH(B85,'00 ACC DETAILS 03'!$E$30:$E$112,0),'00 ACC DETAILS 03'!$A$30:$A$112,'00 ACC DETAILS 03'!$D$30:$D$112)),0) | B85: 2008-W | C85: =C83 | D85: =A85*C85 | E85: =E86+6 | F85: =D85*E85/100 | G85: =D85+F85
A86: =IFERROR((LOOKUP(MATCH(B86,'00 ACC DETAILS 03'!$E$30:$E$112,0),'00 ACC DETAILS 03'!$A$30:$A$112,'00 ACC DETAILS 03'!$D$30:$D$112)),0) | B86: 2009-D | C86: 2250 | D86: =A86*C86 | E86: =E87+6 | F86: =D86*E86/100 | G86: =D86+F86
A87: =IFERROR((LOOKUP(MATCH(B87,'00 ACC DETAILS 03'!$E$30:$E$112,0),'00 ACC DETAILS 03'!$A$30:$A$112,'00 ACC DETAILS 03'!$D$30:$D$112)),0) | B87: 2009-W | C87: =C85 | D87: =A87*C87 | E87: =E88+6 | F87: =D87*E87/100 | G87: =D87+F87
A88: =IFERROR((LOOKUP(MATCH(B88,'00 ACC DETAILS 03'!$E$30:$E$112,0),'00 ACC DETAILS 03'!$A$30:$A$112,'00 ACC DETAILS 03'!$D$30:$D$112)),0) | B88: 2010-D | C88: =C86 | D88: =A88*C88 | E88: =E89+6 | F88: =D88*E88/100 | G88: =D88+F88
A89: =IFERROR((LOOKUP(MATCH(B89,'00 ACC DETAILS 03'!$E$30:$E$112,0),'00 ACC DETAILS 03'!$A$30:$A$112,'00 ACC DETAILS 03'!$D$30:$D$112)),0) | B89: 2010-W | C89: =C87 | D89: =A89*C89 | E89: =E90+6 | F89: =D89*E89/100 | G89: =D89+F89
A90: =IFERROR((LOOKUP(MATCH(B90,'00 ACC DETAILS 03'!$E$30:$E$112,0),'00 ACC DETAILS 03'!$A$30:$A$112,'00 ACC DETAILS 03'!$D$30:$D$112)),0) | B90: 2011-D | C90: =C88 | D90: =A90*C90 | E90: =E91+6 | F90: =D90*E90/100 | G90: =D90+F90
A91: =IFERROR((LOOKUP(MATCH(B91,'00 ACC DETAILS 03'!$E$30:$E$112,0),'00 ACC DETAILS 03'!$A$30:$A$112,'00 ACC DETAILS 03'!$D$30:$D$112)),0) | B91: 2011-W | C91: =C89 | D91: =A91*C91 | E91: =E92+6 | F91: =D91*E91/100 | G91: =D91+F91
A92: =IFERROR((LOOKUP(MATCH(B92,'00 ACC DETAILS 03'!$E$30:$E$112,0),'00 ACC DETAILS 03'!$A$30:$A$112,'00 ACC DETAILS 03'!$D$30:$D$112)),0) | B92: 2012-D | C92: 2550 | D92: =A92*C92 | E92: =E93+6 | F92: =D92*E92/100 | G92: =D92+F92
A93: =IFERROR((LOOKUP(MATCH(B93,'00 ACC DETAILS 03'!$E$30:$E$112,0),'00 ACC DETAILS 03'!$A$30:$A$112,'00 ACC DETAILS 03'!$D$30:$D$112)),0) | B93: 2012-W | C93: 1700 | D93: =A93*C93 | E93: =E94+6 | F93: =D93*E93/100 | G93: =D93+F93
A94: =IFERROR((LOOKUP(MATCH(B94,'00 ACC DETAILS 03'!$E$30:$E$112,0),'00 ACC DETAILS 03'!$A$30:$A$112,'00 ACC DETAILS 03'!$D$30:$D$112)),0) | B94: 2013-D | C94: =17*150 | D94: =A94*C94 | E94: =E95+6 | F94: =D94*E94/100 | G94: =D94+F94
A95: =IFERROR((LOOKUP(MATCH(B95,'00 ACC DETAILS 03'!$E$30:$E$112,0),'00 ACC DETAILS 03'!$A$30:$A$112,'00 ACC DETAILS 03'!$D$30:$D$112)),0) | B95: 2013-W | C95: =17*100 | D95: =A95*C95 | E95: =E96+6 | F95: =D95*E95/100 | G95: =D95+F95
A96: =IFERROR((LOOKUP(MATCH(B96,'00 ACC DETAILS 03'!$E$30:$E$112,0),'00 ACC DETAILS 03'!$A$30:$A$112,'00 ACC DETAILS 03'!$D$30:$D$112)),0) | B96: 2014-D | C96: =C94 | D96: =A96*C96 | E96: =E97+6 | F96: =D96*E96/100 | G96: =D96+F96
A97: =IFERROR((LOOKUP(MATCH(B97,'00 ACC DETAILS 03'!$E$30:$E$112,0),'00 ACC DETAILS 03'!$A$30:$A$112,'00 ACC DETAILS 03'!$D$30:$D$112)),0) | B97: 2014-W | C97: =17*100 | D97: =A97*C97 | E97: =E98+6 | F97: =D97*E97/100 | G97: =D97+F97
A98: =IFERROR((LOOKUP(MATCH(B98,'00 ACC DETAILS 03'!$E$30:$E$112,0),'00 ACC DETAILS 03'!$A$30:$A$112,'00 ACC DETAILS 03'!$D$30:$D$112)),0) | B98: 2015-D | C98: =C96 | D98: =A98*C98 | E98: =E99+6 | F98: =D98*E98/100 | G98: =D98+F98
A99: =IFERROR((LOOKUP(MATCH(B99,'00 ACC DETAILS 03'!$E$30:$E$112,0),'00 ACC DETAILS 03'!$A$30:$A$112,'00 ACC DETAILS 03'!$D$30:$D$112)),0) | B99: 2015-W | C99: =17*100 | D99: =A99*C99 | E99: =E100+6 | F99: =D99*E99/100 | G99: =D99+F99
A100: =IFERROR((LOOKUP(MATCH(B100,'00 ACC DETAILS 03'!$E$30:$E$112,0),'00 ACC DETAILS 03'!$A$30:$A$112,'00 ACC DETAILS 03'!$D$30:$D$112)),0) | B100: 2016-D | C100: =C98 | D100: =A100*C100 | E100: =E101+6 | F100: =D100*E100/100 | G100: =D100+F100
A101: =IFERROR((LOOKUP(MATCH(B101,'00 ACC DETAILS 03'!$E$30:$E$112,0),'00 ACC DETAILS 03'!$A$30:$A$112,'00 ACC DETAILS 03'!$D$30:$D$112)),0) | B101: 2016-W | C101: =17*100 | D101: =A101*C101 | E101: 11 | F101: =D101*E101/100 | G101: =D101+F101
A102: Sub-total | D102: =SUM(D19:D101) | F102: =SUM(F19:F101) | G102: =SUM(G19:G101)
A103: Add old accounts: Prior to July 1,1975 | G103: 0
A104: TOTAL | G104: =G102+G103
A105: Note: If you have any problem with your account and our services, please feel free to see us in our office.
A107: Prepared by: | C107: Checked by: | D107: Recommending Approval: | G107: Approved:
A109: CATHERINE DC. AUSTRIA | C109: MAGNOLIA L. TAYAO | E109: JUANITO C. VALONES | G109: ROBERTO J. DELA CRUZ
A110: Accounting Proc. A | C110: Head, Billing Unit | E110: O&M Chief | G110: Manager, BANE IMO
A119: Republika ng Pilipinas
A120: National Irrigation Administration
A121: (Pambansang Pangasiwaan ng Patubig)
A122: Bulacan – Aurora – Nueva Ecija Irrigation Management Office
A123: Tambubong, San Rafael, Bulacan
A125: Office Address : Tambubong, San Rafael, Bulacan | G125: Telefax No. (044) 766-3888
A126: Telephone Nos. : (044) 766-3888 | G126: TIN No. 000-578-009-000
A127: Email Address : niabaneimoafs@yahoo.com
A129: STATEMENT OF ACCOUNT
A130: =A12
A132: FARMER CODE NO.: | C132: =C14 | F132: WRFT Div. : | G132: =G14
A133: Lot No.: | C133: =C15 | F133: Area:. | G133: =G15
A134: Name of Landowner: | E134: Address:
A135: Name of Farmers: | C135: =C17 | E135: Address:
A136: Area | B136: C. S. | C136: Rate | D136: Principal | E136: %Penalty | F136: Penalty(Cash) | G136: Total
A137: =A19 | B137: 75-W | C137: =1.1*100 | D137: =A137*C137 | F137: =D137*E137/100 | G137: =D137+F137
A138: =A20 | B138: 76-D | C138: =1.1*150 | D138: =A138*C138 | F138: =D138*E138/100 | G138: =D138+F138
A139: =A21 | B139: 76-W | C139: =1.1*100 | D139: =A139*C139 | F139: =D139*E139/100 | G139: =D139+F139
A140: =A22 | B140: 77-D | C140: =1.1*150 | D140: =A140*C140 | F140: =D140*E140/100 | G140: =D140+F140
A141: =A23 | B141: 77-W | C141: =1.1*100 | D141: =A141*C141 | F141: =D141*E141/100 | G141: =D141+F141
A142: =A24 | B142: 78-D | C142: =1.1*150 | D142: =A142*C142 | F142: =D142*E142/100 | G142: =D142+F142
A143: =A25 | B143: 78-W | C143: =1.1*100 | D143: =A143*C143 | F143: =D143*E143/100 | G143: =D143+F143
A144: =A26 | B144: 79-D | C144: =1.1*150 | D144: =A144*C144 | F144: =D144*E144/100 | G144: =D144+F144
A145: =A27 | B145: 79-W | C145: =1.3*100 | D145: =A145*C145 | F145: =D145*E145/100 | G145: =D145+F145
A146: =A28 | B146: 80-D | C146: =1.3*150 | D146: =A146*C146 | F146: =D146*E146/100 | G146: =D146+F146
A147: =A29 | B147: 80-W | C147: =1.3*100 | D147: =A147*C147 | F147: =D147*E147/100 | G147: =D147+F147
A148: =A30 | B148: 81-D | C148: =1.4*150 | D148: =A148*C148 | F148: =D148*E148/100 | G148: =D148+F148
A149: =A31 | B149: 81-W | C149: =1.45*100 | D149: =A149*C149 | F149: =D149*E149/100 | G149: =D149+F149
A150: =A32 | B150: 82-D | C150: =1.55*150 | D150: =A150*C150 | F150: =D150*E150/100 | G150: =D150+F150
...

Sheet 00 ACC DETAILS 04
B2: ACCOUNT DETAILS
B3: Lot No. | C3: 3809
B4: Division | C4: ='00 ACC DETAILS 01'!C4
B5: Name of IA | C5: ='00 ACC DETAILS 01'!C5
B6: Name of Land Owner
B7: First Name | C7: ='00 ACC DETAILS 01'!C7
B8: Middle Name | C8: ='00 ACC DETAILS 01'!C8
B9: Surname | C9: ='00 ACC DETAILS 01'!C9
B10: Name of Farmer/Land Tiller
B11: First Name | C11: MARCELO
B12: Middle Name
B13: Surname | C13: GUINTO
B14: Location of Lot
B15: Baranggay | C15: ='00 ACC DETAILS 01'!C15
B16: Municipality/City | C16: ='00 ACC DETAILS 01'!C16
B17: Province | C17: ='00 ACC DETAILS 01'!C17
B18: Address of Land Owner
B19: Baranggay | C19: ='00 ACC DETAILS 01'!C19
B20: Municipality/City | C20: ='00 ACC DETAILS 01'!C20
B21: Province | C21: ='00 ACC DETAILS 01'!C21
B22: Address of Farmer/Land Tiller
B23: Baranggay | C23: ='00 ACC DETAILS 01'!C23
B24: Municipality/City | C24: ='00 ACC DETAILS 01'!C24
B25: Province | C25: ='00 ACC DETAILS 01'!C25
A28: IRRIGATION FEE REGISTRY (IFR)
B29: Wet/Dry | C29: Year | D29: Area
A30: 1 | E30: =IF(ISBLANK(B30),0,IF(C30<2000,RIGHT(C30,2),C30)&"-"&IF(B30="wet","W","D"))
A31: 2 | E31: =IF(ISBLANK(B31),0,IF(C31<2000,RIGHT(C31,2),C31)&"-"&IF(B31="wet","W","D"))
A32: 3 | E32: =IF(ISBLANK(B32),0,IF(C32<2000,RIGHT(C32,2),C32)&"-"&IF(B32="wet","W","D"))
A33: 4 | E33: =IF(ISBLANK(B33),0,IF(C33<2000,RIGHT(C33,2),C33)&"-"&IF(B33="wet","W","D"))
A34: 5 | E34: =IF(ISBLANK(B34),0,IF(C34<2000,RIGHT(C34,2),C34)&"-"&IF(B34="wet","W","D"))
A35: 6 | E35: =IF(ISBLANK(B35),0,IF(C35<2000,RIGHT(C35,2),C35)&"-"&IF(B35="wet","W","D"))
A36: 7 | E36: =IF(ISBLANK(B36),0,IF(C36<2000,RIGHT(C36,2),C36)&"-"&IF(B36="wet","W","D"))
A37: 8 | E37: =IF(ISBLANK(B37),0,IF(C37<2000,RIGHT(C37,2),C37)&"-"&IF(B37="wet","W","D"))
A38: 9 | E38: =IF(ISBLANK(B38),0,IF(C38<2000,RIGHT(C38,2),C38)&"-"&IF(B38="wet","W","D"))
A39: 10 | E39: =IF(ISBLANK(B39),0,IF(C39<2000,RIGHT(C39,2),C39)&"-"&IF(B39="wet","W","D"))
A40: 11 | E40: =IF(ISBLANK(B40),0,IF(C40<2000,RIGHT(C40,2),C40)&"-"&IF(B40="wet","W","D"))
A41: 12 | E41: =IF(ISBLANK(B41),0,IF(C41<2000,RIGHT(C41,2),C41)&"-"&IF(B41="wet","W","D"))
... A112: 83 | E112: =IF(ISBLANK(B112),0,IF(C112<2000,RIGHT(C112,2),C112)&"-"&IF(B112="wet","W","D"))

Sheet 01 SOA 04
A11: STATEMENT OF ACCOUNT
A12: ="as of "&TEXT(TODAY(),"mmmm dd, yyyy")
A14: FARMER CODE NO.: | F14: WRFT Div. : | G14: ='00 ACC DETAILS 04'!C4&" - "&'00 ACC DETAILS 04'!C5
A15: Lot No.: | C15: ='00 ACC DETAILS 04'!C3 | F15: Area:. | G15: {=IFERROR(0,LOOKUP(2,1/(A19:A101),A19:A101))}
A16: Name of Landowner: | C16: =IF(ISBLANK('00 ACC DETAILS 01'!C8),'00 ACC DETAILS 01'!C7&" "&'00 ACC DETAILS 01'!C9,'00 ACC DETAILS 01'!C7&" "&'00 ACC DETAILS 01'!C8&" "&'00 ACC DETAILS 01'!C9) | E16: Address:
A17: Name of Farmers: | C17: =IF(ISBLANK('00 ACC DETAILS 04'!C12),'00 ACC DETAILS 04'!C11&" "&'00 ACC DETAILS 04'!C13,'00 ACC DETAILS 04'!C11&" "&'00 ACC DETAILS 04'!C12&" "&'00 ACC DETAILS 04'!C13) | E17: Address:
A18: Area | B18: C. S. | C18: Rate | D18: Principal | E18: %Penalty | F18: Penalty(Cash) | G18: Total
A19: =IFERROR((LOOKUP(MATCH(B19,'00 ACC DETAILS 04'!$E$30:$E$112,0),'00 ACC DETAILS 04'!$A$30:$A$112,'00 ACC DETAILS 04'!$D$30:$D$112)),0) | B19: 75-W | C19: =15*100 | D19: =A19*C19 | E19: =E21+12 | F19: =D19*E19/100 | G19: =D19+F19
A20: =IFERROR((LOOKUP(MATCH(B20,'00 ACC DETAILS 04'!$E$30:$E$112,0),'00 ACC DETAILS 04'!$A$30:$A$112,'00 ACC DETAILS 04'!$D$30:$D$112)),0) | B20: 76-D | C20: =15*150 | D20: =A20*C20 | E20: =E22+12 | F20: =D20*E20/100 | G20: =D20+F20
A21: =IFERROR((LOOKUP(MATCH(B21,'00 ACC DETAILS 04'!$E$30:$E$112,0),'00 ACC DETAILS 04'!$A$30:$A$112,'00 ACC DETAILS 04'!$D$30:$D$112)),0) | B21: 76-W | C21: =C19 | D21: =A21*C21 | E21: =E22+12 | F21: =D21*E21/100 | G21: =D21+F21
A22: =IFERROR((LOOKUP(MATCH(B22,'00 ACC DETAILS 04'!$E$30:$E$112,0),'00 ACC DETAILS 04'!$A$30:$A$112,'00 ACC DETAILS 04'!$D$30:$D$112)),0) | B22: 77-D | C22: =C20 | D22: =A22*C22 | E22: =E24+12 | F22: =D22*E22/100 | G22: =D22+F22
A23: =IFERROR((LOOKUP(MATCH(B23,'00 ACC DETAILS 04'!$E$30:$E$112,0),'00 ACC DETAILS 04'!$A$30:$A$112,'00 ACC DETAILS 04'!$D$30:$D$112)),0) | B23: 77-W | C23: =C21 | D23: =A23*C23 | E23: =E24+12 | F23: =D23*E23/100 | G23: =D23+F23
A24: =IFERROR((LOOKUP(MATCH(B24,'00 ACC DETAILS 04'!$E$30:$E$112,0),'00 ACC DETAILS 04'!$A$30:$A$112,'00 ACC DETAILS 04'!$D$30:$D$112)),0) | B24: 78-D | C24: =C22 | D24: =A24*C24 | E24: =E26+6 | F24: =D24*E24/100 | G24: =D24+F24
A25: =IFERROR((LOOKUP(MATCH(B25,'00 ACC DETAILS 04'!$E$30:$E$112,0),'00 ACC DETAILS 04'!$A$30:$A$112,'00 ACC DETAILS 04'!$D$30:$D$112)),0) | B25: 78-W | C25: =C23 | D25: =A25*C25 | E25: =E26+6 | F25: =D25*E25/100 | G25: =D25+F25
A26: =IFERROR((LOOKUP(MATCH(B26,'00 ACC DETAILS 04'!$E$30:$E$112,0),'00 ACC DETAILS 04'!$A$30:$A$112,'00 ACC DETAILS 04'!$D$30:$D$112)),0) | B26: 79-D | C26: =C24 | D26: =A26*C26 | E26: =E27+6 | F26: =D26*E26/100 | G26: =D26+F26
A27: =IFERROR((LOOKUP(MATCH(B27,'00 ACC DETAILS 04'!$E$30:$E$112,0),'00 ACC DETAILS 04'!$A$30:$A$112,'00 ACC DETAILS 04'!$D$30:$D$112)),0) | B27: 79-W | C27: =C25 | D27: =A27*C27 | E27: =E28+6 | F27: =D27*E27/100 | G27: =D27+F27
A28: =IFERROR((LOOKUP(MATCH(B28,'00 ACC DETAILS 04'!$E$30:$E$112,0),'00 ACC DETAILS 04'!$A$30:$A$112,'00 ACC DETAILS 04'!$D$30:$D$112)),0) | B28: 80-D | C28: =C26 | D28: =A28*C28 | E28: =E29+6 | F28: =D28*E28/100 | G28: =D28+F28
A29: =IFERROR((LOOKUP(MATCH(B29,'00 ACC DETAILS 04'!$E$30:$E$112,0),'00 ACC DETAILS 04'!$A$30:$A$112,'00 ACC DETAILS 04'!$D$30:$D$112)),0) | B29: 80-W | C29: =C27 | D29: =A29*C29 | E29: =E30+6 | F29: =D29*E29/100 | G29: =D29+F29
A30: =IFERROR((LOOKUP(MATCH(B30,'00 ACC DETAILS 04'!$E$30:$E$112,0),'00 ACC DETAILS 04'!$A$30:$A$112,'00 ACC DETAILS 04'!$D$30:$D$112)),0) | B30: 81-D | C30: =C28 | D30: =A30*C30 | E30: =E31+6 | F30: =D30*E30/100 | G30: =D30+F30
A31: =IFERROR((LOOKUP(MATCH(B31,'00 ACC DETAILS 04'!$E$30:$E$112,0),'00 ACC DETAILS 04'!$A$30:$A$112,'00 ACC DETAILS 04'!$D$30:$D$112)),0) | B31: 81-W | C31: =C29 | D31: =A31*C31 | E31: =E32+6 | F31: =D31*E31/100 | G31: =D31+F31
A32: =IFERROR((LOOKUP(MATCH(B32,'00 ACC DETAILS 04'!$E$30:$E$112,0),'00 ACC DETAILS 04'!$A$30:$A$112,'00 ACC DETAILS 04'!$D$30:$D$112)),0) | B32: 82-D | C32: =C30 | D32: =A32*C32 | E32: =E33+6 | F32: =D32*E32/100 | G32: =D32+F32
A33: =IFERROR((LOOKUP(MATCH(B33,'00 ACC DETAILS 04'!$E$30:$E$112,0),'00 ACC DETAILS 04'!$A$30:$A$112,'00 ACC DETAILS 04'!$D$30:$D$112)),0) | B33: 82-W | C33: =C31 | D33: =A33*C33 | E33: =E34+6 | F33: =D33*E33/100 | G33: =D33+F33
A34: =IFERROR((LOOKUP(MATCH(B34,'00 ACC DETAILS 04'!$E$30:$E$112,0),'00 ACC DETAILS 04'!$A$30:$A$112,'00 ACC DETAILS 04'!$D$30:$D$112)),0) | B34: 83-D | C34: =C32 | D34: =A34*C34 | E34: =E35+6 | F34: =D34*E34/100 | G34: =D34+F34
A35: =IFERROR((LOOKUP(MATCH(B35,'00 ACC DETAILS 04'!$E$30:$E$112,0),'00 ACC DETAILS 04'!$A$30:$A$112,'00 ACC DETAILS 04'!$D$30:$D$112)),0) | B35: 83-W | C35: =C33 | D35: =A35*C35 | E35: =E36+6 | F35: =D35*E35/100 | G35: =D35+F35
A36: =IFERROR((LOOKUP(MATCH(B36,'00 ACC DETAILS 04'!$E$30:$E$112,0),'00 ACC DETAILS 04'!$A$30:$A$112,'00 ACC DETAILS 04'!$D$30:$D$112)),0) | B36: 84-D | C36: =C34 | D36: =A36*C36 | E36: =E37+6 | F36: =D36*E36/100 | G36: =D36+F36
... A63: =IFERROR((LOOKUP(MATCH(B63,'00 ACC DETAILS 04'!$E$30:$E$112,0),'00 ACC DETAILS 04'!$A$30:$A$112,'00 ACC DETAILS 04'!$D$30:$D$112)),0) | B63: 97-W | C63: =C61 | D63: =A63*C63 | E63: =E64+6 | F63: =D63*E63/100 | G63: =D63+F63
A64: =IFERROR((LOOKUP(MATCH(B64,'00 ACC DETAILS 04'!$E$30:$E$112,0),'00 ACC DETAILS 04'!$A$30:$A$112,'00 ACC DETAILS 04'!$D$30:$D$112)),0) | B64: 98-D | C64: 0 | D64: =A64*C64 | E64: =E65+6 | F64: =D64*E64/100 | G64: =D64+F64
A65: =IFERROR((LOOKUP(MATCH(B65,'00 ACC DETAILS 04'!$E$30:$E$112,0),'00 ACC DETAILS 04'!$A$30:$A$112,'00 ACC DETAILS 04'!$D$30:$D$112)),0) | B65: 98-W | C65: 400 | D65: =A65*C65 | E65: =E66+6 | F65: =D65*E65/100 | G65: =D65+F65
A66: =IFERROR((LOOKUP(MATCH(B66,'00 ACC DETAILS 04'!$E$30:$E$112,0),'00 ACC DETAILS 04'!$A$30:$A$112,'00 ACC DETAILS 04'!$D$30:$D$112)),0) | B66: 99-D | C66: 600 | D66: =A66*C66 | E66: =E67+6 | F66: =D66*E66/100 | G66: =D66+F66
A67: =IFERROR((LOOKUP(MATCH(B67,'00 ACC DETAILS 04'!$E$30:$E$112,0),'00 ACC DETAILS 04'!$A$30:$A$112,'00 ACC DETAILS 04'!$D$30:$D$112)),0) | B67: 99-W | C67: 450 | D67: =A67*C67 | E67: =E68+6 | F67: =D67*E67/100 | G67: =D67+F67
A68: =IFERROR((LOOKUP(MATCH(B68,'00 ACC DETAILS 04'!$E$30:$E$112,0),'00 ACC DETAILS 04'!$A$30:$A$112,'00 ACC DETAILS 04'!$D$30:$D$112)),0) | B68: 2000-D | C68: 750 | D68: =A68*C68 | E68: =E69+6 | F68: =D68*E68/100 | G68: =D68+F68
A69: =IFERROR((LOOKUP(MATCH(B69,'00 ACC DETAILS 04'!$E$30:$E$112,0),'00 ACC DETAILS 04'!$A$30:$A$112,'00 ACC DETAILS 04'!$D$30:$D$112)),0) | B69: 2000-W | C69: =C67 | D69: =A69*C69 | E69: =E70+6 | F69: =D69*E69/100 | G69: =D69+F69
A70: =IFERROR((LOOKUP(MATCH(B70,'00 ACC DETAILS 04'!$E$30:$E$112,0),'00 ACC DETAILS 04'!$A$30:$A$112,'00 ACC DETAILS 04'!$D$30:$D$112)),0) | B70: 2001-D | C70: =C68 | D70: =A70*C70 | E70: =E71+6 | F70: =D70*E70/100 | G70: =D70+F70
A71: =IFERROR((LOOKUP(MATCH(B71,'00 ACC DETAILS 04'!$E$30:$E$112,0),'00 ACC DETAILS 04'!$A$30:$A$112,'00 ACC DETAILS 04'!$D$30:$D$112)),0) | B71: 2001-W | C71: =C63 | D71: =A71*C71 | E71: =E72+6 | F71: =D71*E71/100 | G71: =D71+F71
A72: =IFERROR((LOOKUP(MATCH(B72,'00 ACC DETAILS 04'!$E$30:$E$112,0),'00 ACC DETAILS 04'!$A$30:$A$112,'00 ACC DETAILS 04'!$D$30:$D$112)),0) | B72: 2002-D | C72: =C62 | D72: =A72*C72 | E72: =E73+6 | F72: =D72*E72/100 | G72: =D72+F72
A73: =IFERROR((LOOKUP(MATCH(B73,'00 ACC DETAILS 04'!$E$30:$E$112,0),'00 ACC DETAILS 04'!$A$30:$A$112,'00 ACC DETAILS 04'!$D$30:$D$112)),0) | B73: 2002-W | C73: =C71 | D73: =A73*C73 | E73: =E74+6 | F73: =D73*E73/100 | G73: =D73+F73
A74: =IFERROR((LOOKUP(MATCH(B74,'00 ACC DETAILS 04'!$E$30:$E$112,0),'00 ACC DETAILS 04'!$A$30:$A$112,'00 ACC DETAILS 04'!$D$30:$D$112)),0) | B74: 2003-D | C74: =C72 | D74: =A74*C74 | E74: =E75+6 | F74: =D74*E74/100 | G74: =D74+F74
A75: =IFERROR((LOOKUP(MATCH(B75,'00 ACC DETAILS 04'!$E$30:$E$112,0),'00 ACC DETAILS 04'!$A$30:$A$112,'00 ACC DETAILS 04'!$D$30:$D$112)),0) | B75: 2003-W | C75: =C73 | D75: =A75*C75 | E75: =E76+6 | F75: =D75*E75/100 | G75: =D75+F75
A76: =IFERROR((LOOKUP(MATCH(B76,'00 ACC DETAILS 04'!$E$30:$E$112,0),'00 ACC DETAILS 04'!$A$30:$A$112,'00 ACC DETAILS 04'!$D$30:$D$112)),0) | B76: 2004-D | C76: =C74 | D76: =A76*C76 | E76: =E77+6 | F76: =D76*E76/100 | G76: =D76+F76
A77: =IFERROR((LOOKUP(MATCH(B77,'00 ACC DETAILS 04'!$E$30:$E$112,0),'00 ACC DETAILS 04'!$A$30:$A$112,'00 ACC DETAILS 04'!$D$30:$D$112)),0) | B77: 2004-W | C77: =C75 | D77: =A77*C77 | E77: =E78+6 | F77: =D77*E77/100 | G77: =D77+F77
A78: =IFERROR((LOOKUP(MATCH(B78,'00 ACC DETAILS 04'!$E$30:$E$112,0),'00 ACC DETAILS 04'!$A$30:$A$112,'00 ACC DETAILS 04'!$D$30:$D$112)),0) | B78: 2005-D | C78: =C76 | D78: =A78*C78 | E78: =E79+6 | F78: =D78*E78/100 | G78: =D78+F78
A79: =IFERROR((LOOKUP(MATCH(B79,'00 ACC DETAILS 04'!$E$30:$E$112,0),'00 ACC DETAILS 04'!$A$30:$A$112,'00 ACC DETAILS 04'!$D$30:$D$112)),0) | B79: 2005-W | C79: =C77 | D79: =A79*C79 | E79: =E80+6 | F79: =D79*E79/100 | G79: =D79+F79
A80: =IFERROR((LOOKUP(MATCH(B80,'00 ACC DETAILS 04'!$E$30:$E$112,0),'00 ACC DETAILS 04'!$A$30:$A$112,'00 ACC DETAILS 04'!$D$30:$D$112)),0) | B80: 2006-D | C80: =C78 | D80: =A80*C80 | E80: =E81+6 | F80: =D80*E80/100 | G80: =D80+F80
A81: =IFERROR((LOOKUP(MATCH(B81,'00 ACC DETAILS 04'!$E$30:$E$112,0),'00 ACC DETAILS 04'!$A$30:$A$112,'00 ACC DETAILS 04'!$D$30:$D$112)),0) | B81: 2006-W | C81: =C79 | D81: =A81*C81 | E81: =E82+6 | F81: =D81*E81/100 | G81: =D81+F81
A82: =IFERROR((LOOKUP(MATCH(B82,'00 ACC DETAILS 04'!$E$30:$E$112,0),'00 ACC DETAILS 04'!$A$30:$A$112,'00 ACC DETAILS 04'!$D$30:$D$112)),0) | B82: 2007-D | C82: =C80 | D82: =A82*C82 | E82: =E83+6 | F82: =D82*E82/100 | G82: =D82+F82
A83: =IFERROR((LOOKUP(MATCH(B83,'00 ACC DETAILS 04'!$E$30:$E$112,0),'00 ACC DETAILS 04'!$A$30:$A$112,'00 ACC DETAILS 04'!$D$30:$D$112)),0) | B83: 2007-W | C83: =C81 | D83: =A83*C83 | E83: =E84+6 | F83: =D83*E83/100 | G83: =D83+F83
A84: =IFERROR((LOOKUP(MATCH(B84,'00 ACC DETAILS 04'!$E$30:$E$112,0),'00 ACC DETAILS 04'!$A$30:$A$112,'00 ACC DETAILS 04'!$D$30:$D$112)),0) | B84: 2008-D | C84: =C82 | D84: =A84*C84 | E84: =E85+6 | F84: =D84*E84/100 | G84: =D84+F84
A85: =IFERROR((LOOKUP(MATCH(B85,'00 ACC DETAILS 04'!$E$30:$E$112,0),'00 ACC DETAILS 04'!$A$30:$A$112,'00 ACC DETAILS 04'!$D$30:$D$112)),0) | B85: 2008-W | C85: =C83 | D85: =A85*C85 | E85: =E86+6 | F85: =D85*E85/100 | G85: =D85+F85
A86: =IFERROR((LOOKUP(MATCH(B86,'00 ACC DETAILS 04'!$E$30:$E$112,0),'00 ACC DETAILS 04'!$A$30:$A$112,'00 ACC DETAILS 04'!$D$30:$D$112)),0) | B86: 2009-D | C86: 2250 | D86: =A86*C86 | E86: =E87+6 | F86: =D86*E86/100 | G86: =D86+F86
A87: =IFERROR((LOOKUP(MATCH(B87,'00 ACC DETAILS 04'!$E$30:$E$112,0),'00 ACC DETAILS 04'!$A$30:$A$112,'00 ACC DETAILS 04'!$D$30:$D$112)),0) | B87: 2009-W | C87: =C85 | D87: =A87*C87 | E87: =E88+6 | F87: =D87*E87/100 | G87: =D87+F87
A88: =IFERROR((LOOKUP(MATCH(B88,'00 ACC DETAILS 04'!$E$30:$E$112,0),'00 ACC DETAILS 04'!$A$30:$A$112,'00 ACC DETAILS 04'!$D$30:$D$112)),0) | B88: 2010-D | C88: =C86 | D88: =A88*C88 | E88: =E89+6 | F88: =D88*E88/100 | G88: =D88+F88
A89: =IFERROR((LOOKUP(MATCH(B89,'00 ACC DETAILS 04'!$E$30:$E$112,0),'00 ACC DETAILS 04'!$A$30:$A$112,'00 ACC DETAILS 04'!$D$30:$D$112)),0) | B89: 2010-W | C89: =C87 | D89: =A89*C89 | E89: =E90+6 | F89: =D89*E89/100 | G89: =D89+F89
A90: =IFERROR((LOOKUP(MATCH(B90,'00 ACC DETAILS 04'!$E$30:$E$112,0),'00 ACC DETAILS 04'!$A$30:$A$112,'00 ACC DETAILS 04'!$D$30:$D$112)),0) | B90: 2011-D | C90: =C88 | D90: =A90*C90 | E90: =E91+6 | F90: =D90*E90/100 | G90: =D90+F90
A91: =IFERROR((LOOKUP(MATCH(B91,'00 ACC DETAILS 04'!$E$30:$E$112,0),'00 ACC DETAILS 04'!$A$30:$A$112,'00 ACC DETAILS 04'!$D$30:$D$112)),0) | B91: 2011-W | C91: =C89 | D91: =A91*C91 | E91: =E92+6 | F91: =D91*E91/100 | G91: =D91+F91
A92: =IFERROR((LOOKUP(MATCH(B92,'00 ACC DETAILS 04'!$E$30:$E$112,0),'00 ACC DETAILS 04'!$A$30:$A$112,'00 ACC DETAILS 04'!$D$30:$D$112)),0) | B92: 2012-D | C92: 2550 | D92: =A92*C92 | E92: =E93+6 | F92: =D92*E92/100 | G92: =D92+F92
A93: =IFERROR((LOOKUP(MATCH(B93,'00 ACC DETAILS 04'!$E$30:$E$112,0),'00 ACC DETAILS 04'!$A$30:$A$112,'00 ACC DETAILS 04'!$D$30:$D$112)),0) | B93: 2012-W | C93: 1700 | D93: =A93*C93 | E93: =E94+6 | F93: =D93*E93/100 | G93: =D93+F93
A94: =IFERROR((LOOKUP(MATCH(B94,'00 ACC DETAILS 04'!$E$30:$E$112,0),'00 ACC DETAILS 04'!$A$30:$A$112,'00 ACC DETAILS 04'!$D$30:$D$112)),0) | B94: 2013-D | C94: =17*150 | D94: =A94*C94 | E94: =E95+6 | F94: =D94*E94/100 | G94: =D94+F94
A95: =IFERROR((LOOKUP(MATCH(B95,'00 ACC DETAILS 04'!$E$30:$E$112,0),'00 ACC DETAILS 04'!$A$30:$A$112,'00 ACC DETAILS 04'!$D$30:$D$112)),0) | B95: 2013-W | C95: =17*100 | D95: =A95*C95 | E95: =E96+6 | F95: =D95*E95/100 | G95: =D95+F95
A96: =IFERROR((LOOKUP(MATCH(B96,'00 ACC DETAILS 04'!$E$30:$E$112,0),'00 ACC DETAILS 04'!$A$30:$A$112,'00 ACC DETAILS 04'!$D$30:$D$112)),0) | B96: 2014-D | C96: =C94 | D96: =A96*C96 | E96: =E97+6 | F96: =D96*E96/100 | G96: =D96+F96
A97: =IFERROR((LOOKUP(MATCH(B97,'00 ACC DETAILS 04'!$E$30:$E$112,0),'00 ACC DETAILS 04'!$A$30:$A$112,'00 ACC DETAILS 04'!$D$30:$D$112)),0) | B97: 2014-W | C97: =17*100 | D97: =A97*C97 | E97: =E98+6 | F97: =D97*E97/100 | G97: =D97+F97
A98: =IFERROR((LOOKUP(MATCH(B98,'00 ACC DETAILS 04'!$E$30:$E$112,0),'00 ACC DETAILS 04'!$A$30:$A$112,'00 ACC DETAILS 04'!$D$30:$D$112)),0) | B98: 2015-D | C98: =C96 | D98: =A98*C98 | E98: =E99+6 | F98: =D98*E98/100 | G98: =D98+F98
A99: =IFERROR((LOOKUP(MATCH(B99,'00 ACC DETAILS 04'!$E$30:$E$112,0),'00 ACC DETAILS 04'!$A$30:$A$112,'00 ACC DETAILS 04'!$D$30:$D$112)),0) | B99: 2015-W | C99: =17*100 | D99: =A99*C99 | E99: =E100+6 | F99: =D99*E99/100 | G99: =D99+F99
A100: =IFERROR((LOOKUP(MATCH(B100,'00 ACC DETAILS 04'!$E$30:$E$112,0),'00 ACC DETAILS 04'!$A$30:$A$112,'00 ACC DETAILS 04'!$D$30:$D$112)),0) | B100: 2016-D | C100: =C98 | D100: =A100*C100 | E100: =E101+6 | F100: =D100*E100/100 | G100: =D100+F100
A101: =IFERROR((LOOKUP(MATCH(B101,'00 ACC DETAILS 04'!$E$30:$E$112,0),'00 ACC DETAILS 04'!$A$30:$A$112,'00 ACC DETAILS 04'!$D$30:$D$112)),0) | B101: 2016-W | C101: =17*100 | D101: =A101*C101 | E101: 11 | F101: =D101*E101/100 | G101: =D101+F101
A102: Sub-total | D102: =SUM(D19:D101) | F102: =SUM(F19:F101) | G102: =SUM(G19:G101)
A103: Add old accounts: Prior to July 1,1975 | G103: 0
A104: TOTAL | G104: =G102+G103
A105: Note: If you have any problem with your account and our services, please feel free to see us in our office.
A107: Prepared by: | C107: Checked by: | D107: Recommending Approval: | G107: Approved:
A109: CATHERINE DC. AUSTRIA | C109: MAGNOLIA L. TAYAO | E109: JUANITO C. VALONES | G109: ROBERTO J. DELA CRUZ
A110: Accounting Proc. A | C110: Head, Billing Unit | E110: O&M Chief | G110: Manager, BANE IMO
A119: Republika ng Pilipinas
A120: National Irrigation Administration
A121: (Pambansang Pangasiwaan ng Patubig)
A122: Bulacan – Aurora – Nueva Ecija Irrigation Management Office
A123: Tambubong, San Rafael, Bulacan
A125: Office Address : Tambubong, San Rafael, Bulacan | G125: Telefax No. (044) 766-3888
A126: Telephone Nos. : (044) 766-3888 | G126: TIN No. 000-578-009-000
A127: Email Address : niabaneimoafs@yahoo.com
A129: STATEMENT OF ACCOUNT
A130: =A12
A132: FARMER CODE NO.: | C132: =C14 | F132: WRFT Div. : | G132: =G14
A133: Lot No.: | C133: =C15 | F133: Area:. | G133: =G15
A134: Name of Landowner: | E134: Address:
A135: Name of Farmers: | C135: =C17 | E135: Address:
A136: Area | B136: C. S. | C136: Rate | D136: Principal | E136: %Penalty | F136: Penalty(Cash) | G136: Total
A137: =A19 | B137: 75-W | C137: =1.1*100 | D137: =A137*C137 | F137: =D137*E137/100 | G137: =D137+F137
A138: =A20 | B138: 76-D | C138: =1.1*150 | D138: =A138*C138 | F138: =D138*E138/100 | G138: =D138+F138
A139: =A21 | B139: 76-W | C139: =1.1*100 | D139: =A139*C139 | F139: =D139*E139/100 | G139: =D139+F139
A140: =A22 | B140: 77-D | C140: =1.1*150 | D140: =A140*C140 | F140: =D140*E140/100 | G140: =D140+F140
A141: =A23 | B141: 77-W | C141: =1.1*100 | D141: =A141*C141 | F141: =D141*E141/100 | G141: =D141+F141
A142: =A24 | B142: 78-D | C142: =1.1*150 | D142: =A142*C142 | F142: =D142*E142/100 | G142: =D142+F142
A143: =A25 | B143: 78-W | C143: =1.1*100 | D143: =A143*C143 | F143: =D143*E143/100 | G143: =D143+F143
A144: =A26 | B144: 79-D | C144: =1.1*150 | D144: =A144*C144 | F144: =D144*E144/100 | G144: =D144+F144
A145: =A27 | B145: 79-W | C145: =1.3*100 | D145: =A145*C145 | F145: =D145*E145/100 | G145: =D145+F145
A146: =A28 | B146: 80-D | C146: =1.3*150 | D146: =A146*C146 | F146: =D146*E146/100 | G146: =D146+F146
A147: =A29 | B147: 80-W | C147: =1.3*100 | D147: =A147*C147 | F147: =D147*E147/100 | G147: =D147+F147
A148: =A30 | B148: 81-D | C148: =1.4*150 | D148: =A148*C148 | F148: =D148*E148/100 | G148: =D148+F148
A149: =A31 | B149: 81-W | C149: =1.45*100 | D149: =A149*C149 | F149: =D149*E149/100 | G149: =D149+F149
A150: =A32 | B150: 82-D | C150: =1.55*150 | D150: =A150*C150 | F150: =D150*E150/100 | G150: =D150+F150
...

Sheet 00 ACC DETAILS 05
B2: ACCOUNT DETAILS
B3: Lot No. | C3: 3809
B4: Division | C4: ='00 ACC DETAILS 01'!C4
B5: Name of IA | C5: ='00 ACC DETAILS 01'!C5
B6: Name of Land Owner
B7: First Name | C7: ='00 ACC DETAILS 01'!C7
B8: Middle Name | C8: ='00 ACC DETAILS 01'!C8
B9: Surname | C9: ='00 ACC DETAILS 01'!C9
B10: Name of Farmer/Land Tiller
B11: First Name | C11: MARCELO
B12: Middle Name
B13: Surname | C13: GUINTO
B14: Location of Lot
B15: Baranggay | C15: ='00 ACC DETAILS 01'!C15
B16: Municipality/City | C16: ='00 ACC DETAILS 01'!C16
B17: Province | C17: ='00 ACC DETAILS 01'!C17
B18: Address of Land Owner
B19: Baranggay | C19: ='00 ACC DETAILS 01'!C19
B20: Municipality/City | C20: ='00 ACC DETAILS 01'!C20
B21: Province | C21: ='00 ACC DETAILS 01'!C21
B22: Address of Farmer/Land Tiller
B23: Baranggay | C23: ='00 ACC DETAILS 01'!C23
B24: Municipality/City | C24: ='00 ACC DETAILS 01'!C24
B25: Province | C25: ='00 ACC DETAILS 01'!C25
A28: IRRIGATION FEE REGISTRY (IFR)
B29: Wet/Dry | C29: Year | D29: Area
A30: 1 | E30: =IF(ISBLANK(B30),0,IF(C30<2000,RIGHT(C30,2),C30)&"-"&IF(B30="wet","W","D"))
A31: 2 | E31: =IF(ISBLANK(B31),0,IF(C31<2000,RIGHT(C31,2),C31)&"-"&IF(B31="wet","W","D"))
A32: 3 | E32: =IF(ISBLANK(B32),0,IF(C32<2000,RIGHT(C32,2),C32)&"-"&IF(B32="wet","W","D"))
A33: 4 | E33: =IF(ISBLANK(B33),0,IF(C33<2000,RIGHT(C33,2),C33)&"-"&IF(B33="wet","W","D"))
A34: 5 | E34: =IF(ISBLANK(B34),0,IF(C34<2000,RIGHT(C34,2),C34)&"-"&IF(B34="wet","W","D"))
A35: 6 | E35: =IF(ISBLANK(B35),0,IF(C35<2000,RIGHT(C35,2),C35)&"-"&IF(B35="wet","W","D"))
A36: 7 | E36: =IF(ISBLANK(B36),0,IF(C36<2000,RIGHT(C36,2),C36)&"-"&IF(B36="wet","W","D"))
A37: 8 | E37: =IF(ISBLANK(B37),0,IF(C37<2000,RIGHT(C37,2),C37)&"-"&IF(B37="wet","W","D"))
A38: 9 | E38: =IF(ISBLANK(B38),0,IF(C38<2000,RIGHT(C38,2),C38)&"-"&IF(B38="wet","W","D"))
A39: 10 | E39: =IF(ISBLANK(B39),0,IF(C39<2000,RIGHT(C39,2),C39)&"-"&IF(B39="wet","W","D"))
A40: 11 | E40: =IF(ISBLANK(B40),0,IF(C40<2000,RIGHT(C40,2),C40)&"-"&IF(B40="wet","W","D"))
A41: 12 | E41: =IF(ISBLANK(B41),0,IF(C41<2000,RIGHT(C41,2),C41)&"-"&IF(B41="wet","W","D"))
... A112: 83 | E112: =IF(ISBLANK(B112),0,IF(C112<2000,RIGHT(C112,2),C112)&"-"&IF(B112="wet","W","D"))

Sheet 01 SOA 05
A11: STATEMENT OF ACCOUNT
A12: ="as of "&TEXT(TODAY(),"mmmm dd, yyyy")
A14: FARMER CODE NO.: | F14: WRFT Div. : | G14: ='00 ACC DETAILS 05'!C4&" - "&'00 ACC DETAILS 05'!C5
A15: Lot No.: | C15: ='00 ACC DETAILS 05'!C3 | F15: Area:. | G15: {=IFERROR(0,LOOKUP(2,1/(A19:A101),A19:A101))}
A16: Name of Landowner: | C16: =IF(ISBLANK('00 ACC DETAILS 01'!C8),'00 ACC DETAILS 01'!C7&" "&'00 ACC DETAILS 01'!C9,'00 ACC DETAILS 01'!C7&" "&'00 ACC DETAILS 01'!C8&" "&'00 ACC DETAILS 01'!C9) | E16: Address:
A17: Name of Farmers: | C17: =IF(ISBLANK('00 ACC DETAILS 05'!C12),'00 ACC DETAILS 05'!C11&" "&'00 ACC DETAILS 05'!C13,'00 ACC DETAILS 05'!C11&" "&'00 ACC DETAILS 05'!C12&" "&'00 ACC DETAILS 05'!C13) | E17: Address:
A18: Area | B18: C. S. | C18: Rate | D18: Principal | E18: %Penalty | F18: Penalty(Cash) | G18: Total
A19: =IFERROR((LOOKUP(MATCH(B19,'00 ACC DETAILS 05'!$E$30:$E$112,0),'00 ACC DETAILS 05'!$A$30:$A$112,'00 ACC DETAILS 05'!$D$30:$D$112)),0) | B19: 75-W | C19: =15*100 | D19: =A19*C19 | E19: =E21+12 | F19: =D19*E19/100 | G19: =D19+F19
A20: =IFERROR((LOOKUP(MATCH(B20,'00 ACC DETAILS 05'!$E$30:$E$112,0),'00 ACC DETAILS 05'!$A$30:$A$112,'00 ACC DETAILS 05'!$D$30:$D$112)),0) | B20: 76-D | C20: =15*150 | D20: =A20*C20 | E20: =E22+12 | F20: =D20*E20/100 | G20: =D20+F20
A21: =IFERROR((LOOKUP(MATCH(B21,'00 ACC DETAILS 05'!$E$30:$E$112,0),'00 ACC DETAILS 05'!$A$30:$A$112,'00 ACC DETAILS 05'!$D$30:$D$112)),0) | B21: 76-W | C21: =C19 | D21: =A21*C21 | E21: =E22+12 | F21: =D21*E21/100 | G21: =D21+F21
A22: =IFERROR((LOOKUP(MATCH(B22,'00 ACC DETAILS 05'!$E$30:$E$112,0),'00 ACC DETAILS 05'!$A$30:$A$112,'00 ACC DETAILS 05'!$D$30:$D$112)),0) | B22: 77-D | C22: =C20 | D22: =A22*C22 | E22: =E24+12 | F22: =D22*E22/100 | G22: =D22+F22
A23: =IFERROR((LOOKUP(MATCH(B23,'00 ACC DETAILS 05'!$E$30:$E$112,0),'00 ACC DETAILS 05'!$A$30:$A$112,'00 ACC DETAILS 05'!$D$30:$D$112)),0) | B23: 77-W | C23: =C21 | D23: =A23*C23 | E23: =E24+12 | F23: =D23*E23/100 | G23: =D23+F23
A24: =IFERROR((LOOKUP(MATCH(B24,'00 ACC DETAILS 05'!$E$30:$E$112,0),'00 ACC DETAILS 05'!$A$30:$A$112,'00 ACC DETAILS 05'!$D$30:$D$112)),0) | B24: 78-D | C24: =C22 | D24: =A24*C24 | E24: =E26+6 | F24: =D24*E24/100 | G24: =D24+F24
A25: =IFERROR((LOOKUP(MATCH(B25,'00 ACC DETAILS 05'!$E$30:$E$112,0),'00 ACC DETAILS 05'!$A$30:$A$112,'00 ACC DETAILS 05'!$D$30:$D$112)),0) | B25: 78-W | C25: =C23 | D25: =A25*C25 | E25: =E26+6 | F25: =D25*E25/100 | G25: =D25+F25
A26: =IFERROR((LOOKUP(MATCH(B26,'00 ACC DETAILS 05'!$E$30:$E$112,0),'00 ACC DETAILS 05'!$A$30:$A$112,'00 ACC DETAILS 05'!$D$30:$D$112)),0) | B26: 79-D | C26: =C24 | D26: =A26*C26 | E26: =E27+6 | F26: =D26*E26/100 | G26: =D26+F26
A27: =IFERROR((LOOKUP(MATCH(B27,'00 ACC DETAILS 05'!$E$30:$E$112,0),'00 ACC DETAILS 05'!$A$30:$A$112,'00 ACC DETAILS 05'!$D$30:$D$112)),0) | B27: 79-W | C27: =C25 | D27: =A27*C27 | E27: =E28+6 | F27: =D27*E27/100 | G27: =D27+F27
A28: =IFERROR((LOOKUP(MATCH(B28,'00 ACC DETAILS 05'!$E$30:$E$112,0),'00 ACC DETAILS 05'!$A$30:$A$112,'00 ACC DETAILS 05'!$D$30:$D$112)),0) | B28: 80-D | C28: =C26 | D28: =A28*C28 | E28: =E29+6 | F28: =D28*E28/100 | G28: =D28+F28
A29: =IFERROR((LOOKUP(MATCH(B29,'00 ACC DETAILS 05'!$E$30:$E$112,0),'00 ACC DETAILS 05'!$A$30:$A$112,'00 ACC DETAILS 05'!$D$30:$D$112)),0) | B29: 80-W | C29: =C27 | D29: =A29*C29 | E29: =E30+6 | F29: =D29*E29/100 | G29: =D29+F29
A30: =IFERROR((LOOKUP(MATCH(B30,'00 ACC DETAILS 05'!$E$30:$E$112,0),'00 ACC DETAILS 05'!$A$30:$A$112,'00 ACC DETAILS 05'!$D$30:$D$112)),0) | B30: 81-D | C30: =C28 | D30: =A30*C30 | E30: =E31+6 | F30: =D30*E30/100 | G30: =D30+F30
A31: =IFERROR((LOOKUP(MATCH(B31,'00 ACC DETAILS 05'!$E$30:$E$112,0),'00 ACC DETAILS 05'!$A$30:$A$112,'00 ACC DETAILS 05'!$D$30:$D$112)),0) | B31: 81-W | C31: =C29 | D31: =A31*C31 | E31: =E32+6 | F31: =D31*E31/100 | G31: =D31+F31
A32: =IFERROR((LOOKUP(MATCH(B32,'00 ACC DETAILS 05'!$E$30:$E$112,0),'00 ACC DETAILS 05'!$A$30:$A$112,'00 ACC DETAILS 05'!$D$30:$D$112)),0) | B32: 82-D | C32: =C30 | D32: =A32*C32 | E32: =E33+6 | F32: =D32*E32/100 | G32: =D32+F32
A33: =IFERROR((LOOKUP(MATCH(B33,'00 ACC DETAILS 05'!$E$30:$E$112,0),'00 ACC DETAILS 05'!$A$30:$A$112,'00 ACC DETAILS 05'!$D$30:$D$112)),0) | B33: 82-W | C33: =C31 | D33: =A33*C33 | E33: =E34+6 | F33: =D33*E33/100 | G33: =D33+F33
A34: =IFERROR((LOOKUP(MATCH(B34,'00 ACC DETAILS 05'!$E$30:$E$112,0),'00 ACC DETAILS 05'!$A$30:$A$112,'00 ACC DETAILS 05'!$D$30:$D$112)),0) | B34: 83-D | C34: =C32 | D34: =A34*C34 | E34: =E35+6 | F34: =D34*E34/100 | G34: =D34+F34
A35: =IFERROR((LOOKUP(MATCH(B35,'00 ACC DETAILS 05'!$E$30:$E$112,0),'00 ACC DETAILS 05'!$A$30:$A$112,'00 ACC DETAILS 05'!$D$30:$D$112)),0) | B35: 83-W | C35: =C33 | D35: =A35*C35 | E35: =E36+6 | F35: =D35*E35/100 | G35: =D35+F35
A36: =IFERROR((LOOKUP(MATCH(B36,'00 ACC DETAILS 05'!$E$30:$E$112,0),'00 ACC DETAILS 05'!$A$30:$A$112,'00 ACC DETAILS 05'!$D$30:$D$112)),0) | B36: 84-D | C36: =C34 | D36: =A36*C36 | E36: =E37+6 | F36: =D36*E36/100 | G36: =D36+F36
... A63: =IFERROR((LOOKUP(MATCH(B63,'00 ACC DETAILS 05'!$E$30:$E$112,0),'00 ACC DETAILS 05'!$A$30:$A$112,'00 ACC DETAILS 05'!$D$30:$D$112)),0) | B63: 97-W | C63: =C61 | D63: =A63*C63 | E63: =E64+6 | F63: =D63*E63/100 | G63: =D63+F63
A64: =IFERROR((LOOKUP(MATCH(B64,'00 ACC DETAILS 05'!$E$30:$E$112,0),'00 ACC DETAILS 05'!$A$30:$A$112,'00 ACC DETAILS 05'!$D$30:$D$112)),0) | B64: 98-D | C64: 0 | D64: =A64*C64 | E64: =E65+6 | F64: =D64*E64/100 | G64: =D64+F64
A65: =IFERROR((LOOKUP(MATCH(B65,'00 ACC DETAILS 05'!$E$30:$E$112,0),'00 ACC DETAILS 05'!$A$30:$A$112,'00 ACC DETAILS 05'!$D$30:$D$112)),0) | B65: 98-W | C65: 400 | D65: =A65*C65 | E65: =E66+6 | F65: =D65*E65/100 | G65: =D65+F65
A66: =IFERROR((LOOKUP(MATCH(B66,'00 ACC DETAILS 05'!$E$30:$E$112,0),'00 ACC DETAILS 05'!$A$30:$A$112,'00 ACC DETAILS 05'!$D$30:$D$112)),0) | B66: 99-D | C66: 600 | D66: =A66*C66 | E66: =E67+6 | F66: =D66*E66/100 | G66: =D66+F66
A67: =IFERROR((LOOKUP(MATCH(B67,'00 ACC DETAILS 05'!$E$30:$E$112,0),'00 ACC DETAILS 05'!$A$30:$A$112,'00 ACC DETAILS 05'!$D$30:$D$112)),0) | B67: 99-W | C67: 450 | D67: =A67*C67 | E67: =E68+6 | F67: =D67*E67/100 | G67: =D67+F67
A68: =IFERROR((LOOKUP(MATCH(B68,'00 ACC DETAILS 05'!$E$30:$E$112,0),'00 ACC DETAILS 05'!$A$30:$A$112,'00 ACC DETAILS 05'!$D$30:$D$112)),0) | B68: 2000-D | C68: 750 | D68: =A68*C68 | E68: =E69+6 | F68: =D68*E68/100 | G68: =D68+F68
A69: =IFERROR((LOOKUP(MATCH(B69,'00 ACC DETAILS 05'!$E$30:$E$112,0),'00 ACC DETAILS 05'!$A$30:$A$112,'00 ACC DETAILS 05'!$D$30:$D$112)),0) | B69: 2000-W | C69: =C67 | D69: =A69*C69 | E69: =E70+6 | F69: =D69*E69/100 | G69: =D69+F69
A70: =IFERROR((LOOKUP(MATCH(B70,'00 ACC DETAILS 05'!$E$30:$E$112,0),'00 ACC DETAILS 05'!$A$30:$A$112,'00 ACC DETAILS 05'!$D$30:$D$112)),0) | B70: 2001-D | C70: =C68 | D70: =A70*C70 | E70: =E71+6 | F70: =D70*E70/100 | G70: =D70+F70
A71: =IFERROR((LOOKUP(MATCH(B71,'00 ACC DETAILS 05'!$E$30:$E$112,0),'00 ACC DETAILS 05'!$A$30:$A$112,'00 ACC DETAILS 05'!$D$30:$D$112)),0) | B71: 2001-W | C71: =C63 | D71: =A71*C71 | E71: =E72+6 | F71: =D71*E71/100 | G71: =D71+F71
A72: =IFERROR((LOOKUP(MATCH(B72,'00 ACC DETAILS 05'!$E$30:$E$112,0),'00 ACC DETAILS 05'!$A$30:$A$112,'00 ACC DETAILS 05'!$D$30:$D$112)),0) | B72: 2002-D | C72: =C62 | D72: =A72*C72 | E72: =E73+6 | F72: =D72*E72/100 | G72: =D72+F72
A73: =IFERROR((LOOKUP(MATCH(B73,'00 ACC DETAILS 05'!$E$30:$E$112,0),'00 ACC DETAILS 05'!$A$30:$A$112,'00 ACC DETAILS 05'!$D$30:$D$112)),0) | B73: 2002-W | C73: =C71 | D73: =A73*C73 | E73: =E74+6 | F73: =D73*E73/100 | G73: =D73+F73
A74: =IFERROR((LOOKUP(MATCH(B74,'00 ACC DETAILS 05'!$E$30:$E$112,0),'00 ACC DETAILS 05'!$A$30:$A$112,'00 ACC DETAILS 05'!$D$30:$D$112)),0) | B74: 2003-D | C74: =C72 | D74: =A74*C74 | E74: =E75+6 | F74: =D74*E74/100 | G74: =D74+F74
A75: =IFERROR((LOOKUP(MATCH(B75,'00 ACC DETAILS 05'!$E$30:$E$112,0),'00 ACC DETAILS 05'!$A$30:$A$112,'00 ACC DETAILS 05'!$D$30:$D$112)),0) | B75: 2003-W | C75: =C73 | D75: =A75*C75 | E75: =E76+6 | F75: =D75*E75/100 | G75: =D75+F75
A76: =IFERROR((LOOKUP(MATCH(B76,'00 ACC DETAILS 05'!$E$30:$E$112,0),'00 ACC DETAILS 05'!$A$30:$A$112,'00 ACC DETAILS 05'!$D$30:$D$112)),0) | B76: 2004-D | C76: =C74 | D76: =A76*C76 | E76: =E77+6 | F76: =D76*E76/100 | G76: =D76+F76
A77: =IFERROR((LOOKUP(MATCH(B77,'00 ACC DETAILS 05'!$E$30:$E$112,0),'00 ACC DETAILS 05'!$A$30:$A$112,'00 ACC DETAILS 05'!$D$30:$D$112)),0) | B77: 2004-W | C77: =C75 | D77: =A77*C77 | E77: =E78+6 | F77: =D77*E77/100 | G77: =D77+F77
A78: =IFERROR((LOOKUP(MATCH(B78,'00 ACC DETAILS 05'!$E$30:$E$112,0),'00 ACC DETAILS 05'!$A$30:$A$112,'00 ACC DETAILS 05'!$D$30:$D$112)),0) | B78: 2005-D | C78: =C76 | D78: =A78*C78 | E78: =E79+6 | F78: =D78*E78/100 | G78: =D78+F78
A79: =IFERROR((LOOKUP(MATCH(B79,'00 ACC DETAILS 05'!$E$30:$E$112,0),'00 ACC DETAILS 05'!$A$30:$A$112,'00 ACC DETAILS 05'!$D$30:$D$112)),0) | B79: 2005-W | C79: =C77 | D79: =A79*C79 | E79: =E80+6 | F79: =D79*E79/100 | G79: =D79+F79
A80: =IFERROR((LOOKUP(MATCH(B80,'00 ACC DETAILS 05'!$E$30:$E$112,0),'00 ACC DETAILS 05'!$A$30:$A$112,'00 ACC DETAILS 05'!$D$30:$D$112)),0) | B80: 2006-D | C80: =C78 | D80: =A80*C80 | E80: =E81+6 | F80: =D80*E80/100 | G80: =D80+F80
A81: =IFERROR((LOOKUP(MATCH(B81,'00 ACC DETAILS 05'!$E$30:$E$112,0),'00 ACC DETAILS 05'!$A$30:$A$112,'00 ACC DETAILS 05'!$D$30:$D$112)),0) | B81: 2006-W | C81: =C79 | D81: =A81*C81 | E81: =E82+6 | F81: =D81*E81/100 | G81: =D81+F81
A82: =IFERROR((LOOKUP(MATCH(B82,'00 ACC DETAILS 05'!$E$30:$E$112,0),'00 ACC DETAILS 05'!$A$30:$A$112,'00 ACC DETAILS 05'!$D$30:$D$112)),0) | B82: 2007-D | C82: =C80 | D82: =A82*C82 | E82: =E83+6 | F82: =D82*E82/100 | G82: =D82+F82
A83: =IFERROR((LOOKUP(MATCH(B83,'00 ACC DETAILS 05'!$E$30:$E$112,0),'00 ACC DETAILS 05'!$A$30:$A$112,'00 ACC DETAILS 05'!$D$30:$D$112)),0) | B83: 2007-W | C83: =C81 | D83: =A83*C83 | E83: =E84+6 | F83: =D83*E83/100 | G83: =D83+F83
A84: =IFERROR((LOOKUP(MATCH(B84,'00 ACC DETAILS 05'!$E$30:$E$112,0),'00 ACC DETAILS 05'!$A$30:$A$112,'00 ACC DETAILS 05'!$D$30:$D$112)),0) | B84: 2008-D | C84: =C82 | D84: =A84*C84 | E84: =E85+6 | F84: =D84*E84/100 | G84: =D84+F84
A85: =IFERROR((LOOKUP(MATCH(B85,'00 ACC DETAILS 05'!$E$30:$E$112,0),'00 ACC DETAILS 05'!$A$30:$A$112,'00 ACC DETAILS 05'!$D$30:$D$112)),0) | B85: 2008-W | C85: =C83 | D85: =A85*C85 | E85: =E86+6 | F85: =D85*E85/100 | G85: =D85+F85
A86: =IFERROR((LOOKUP(MATCH(B86,'00 ACC DETAILS 05'!$E$30:$E$112,0),'00 ACC DETAILS 05'!$A$30:$A$112,'00 ACC DETAILS 05'!$D$30:$D$112)),0) | B86: 2009-D | C86: 2250 | D86: =A86*C86 | E86: =E87+6 | F86: =D86*E86/100 | G86: =D86+F86
A87: =IFERROR((LOOKUP(MATCH(B87,'00 ACC DETAILS 05'!$E$30:$E$112,0),'00 ACC DETAILS 05'!$A$30:$A$112,'00 ACC DETAILS 05'!$D$30:$D$112)),0) | B87: 2009-W | C87: =C85 | D87: =A87*C87 | E87: =E88+6 | F87: =D87*E87/100 | G87: =D87+F87
A88: =IFERROR((LOOKUP(MATCH(B88,'00 ACC DETAILS 05'!$E$30:$E$112,0),'00 ACC DETAILS 05'!$A$30:$A$112,'00 ACC DETAILS 05'!$D$30:$D$112)),0) | B88: 2010-D | C88: =C86 | D88: =A88*C88 | E88: =E89+6 | F88: =D88*E88/100 | G88: =D88+F88
A89: =IFERROR((LOOKUP(MATCH(B89,'00 ACC DETAILS 05'!$E$30:$E$112,0),'00 ACC DETAILS 05'!$A$30:$A$112,'00 ACC DETAILS 05'!$D$30:$D$112)),0) | B89: 2010-W | C89: =C87 | D89: =A89*C89 | E89: =E90+6 | F89: =D89*E89/100 | G89: =D89+F89
A90: =IFERROR((LOOKUP(MATCH(B90,'00 ACC DETAILS 05'!$E$30:$E$112,0),'00 ACC DETAILS 05'!$A$30:$A$112,'00 ACC DETAILS 05'!$D$30:$D$112)),0) | B90: 2011-D | C90: =C88 | D90: =A90*C90 | E90: =E91+6 | F90: =D90*E90/100 | G90: =D90+F90
A91: =IFERROR((LOOKUP(MATCH(B91,'00 ACC DETAILS 05'!$E$30:$E$112,0),'00 ACC DETAILS 05'!$A$30:$A$112,'00 ACC DETAILS 05'!$D$30:$D$112)),0) | B91: 2011-W | C91: =C89 | D91: =A91*C91 | E91: =E92+6 | F91: =D91*E91/100 | G91: =D91+F91
A92: =IFERROR((LOOKUP(MATCH(B92,'00 ACC DETAILS 05'!$E$30:$E$112,0),'00 ACC DETAILS 05'!$A$30:$A$112,'00 ACC DETAILS 05'!$D$30:$D$112)),0) | B92: 2012-D | C92: 2550 | D92: =A92*C92 | E92: =E93+6 | F92: =D92*E92/100 | G92: =D92+F92
A93: =IFERROR((LOOKUP(MATCH(B93,'00 ACC DETAILS 05'!$E$30:$E$112,0),'00 ACC DETAILS 05'!$A$30:$A$112,'00 ACC DETAILS 05'!$D$30:$D$112)),0) | B93: 2012-W | C93: 1700 | D93: =A93*C93 | E93: =E94+6 | F93: =D93*E93/100 | G93: =D93+F93
A94: =IFERROR((LOOKUP(MATCH(B94,'00 ACC DETAILS 05'!$E$30:$E$112,0),'00 ACC DETAILS 05'!$A$30:$A$112,'00 ACC DETAILS 05'!$D$30:$D$112)),0) | B94: 2013-D | C94: =17*150 | D94: =A94*C94 | E94: =E95+6 | F94: =D94*E94/100 | G94: =D94+F94
A95: =IFERROR((LOOKUP(MATCH(B95,'00 ACC DETAILS 05'!$E$30:$E$112,0),'00 ACC DETAILS 05'!$A$30:$A$112,'00 ACC DETAILS 05'!$D$30:$D$112)),0) | B95: 2013-W | C95: =17*100 | D95: =A95*C95 | E95: =E96+6 | F95: =D95*E95/100 | G95: =D95+F95
A96: =IFERROR((LOOKUP(MATCH(B96,'00 ACC DETAILS 05'!$E$30:$E$112,0),'00 ACC DETAILS 05'!$A$30:$A$112,'00 ACC DETAILS 05'!$D$30:$D$112)),0) | B96: 2014-D | C96: =C94 | D96: =A96*C96 | E96: =E97+6 | F96: =D96*E96/100 | G96: =D96+F96
A97: =IFERROR((LOOKUP(MATCH(B97,'00 ACC DETAILS 05'!$E$30:$E$112,0),'00 ACC DETAILS 05'!$A$30:$A$112,'00 ACC DETAILS 05'!$D$30:$D$112)),0) | B97: 2014-W | C97: =17*100 | D97: =A97*C97 | E97: =E98+6 | F97: =D97*E97/100 | G97: =D97+F97
A98: =IFERROR((LOOKUP(MATCH(B98,'00 ACC DETAILS 05'!$E$30:$E$112,0),'00 ACC DETAILS 05'!$A$30:$A$112,'00 ACC DETAILS 05'!$D$30:$D$112)),0) | B98: 2015-D | C98: =C96 | D98: =A98*C98 | E98: =E99+6 | F98: =D98*E98/100 | G98: =D98+F98
A99: =IFERROR((LOOKUP(MATCH(B99,'00 ACC DETAILS 05'!$E$30:$E$112,0),'00 ACC DETAILS 05'!$A$30:$A$112,'00 ACC DETAILS 05'!$D$30:$D$112)),0) | B99: 2015-W | C99: =17*100 | D99: =A99*C99 | E99: =E100+6 | F99: =D99*E99/100 | G99: =D99+F99
A100: =IFERROR((LOOKUP(MATCH(B100,'00 ACC DETAILS 05'!$E$30:$E$112,0),'00 ACC DETAILS 05'!$A$30:$A$112,'00 ACC DETAILS 05'!$D$30:$D$112)),0) | B100: 2016-D | C100: =C98 | D100: =A100*C100 | E100: =E101+6 | F100: =D100*E100/100 | G100: =D100+F100
A101: =IFERROR((LOOKUP(MATCH(B101,'00 ACC DETAILS 05'!$E$30:$E$112,0),'00 ACC DETAILS 05'!$A$30:$A$112,'00 ACC DETAILS 05'!$D$30:$D$112)),0) | B101: 2016-W | C101: =17*100 | D101: =A101*C101 | E101: 11 | F101: =D101*E101/100 | G101: =D101+F101
A102: Sub-total | D102: =SUM(D19:D101) | F102: =SUM(F19:F101) | G102: =SUM(G19:G101)
A103: Add old accounts: Prior to July 1,1975 | G103: 0
A104: TOTAL | G104: =G102+G103
A105: Note: If you have any problem with your account and our services, please feel free to see us in our office.
A107: Prepared by: | C107: Checked by: | D107: Recommending Approval: | G107: Approved:
A109: CATHERINE DC. AUSTRIA | C109: MAGNOLIA L. TAYAO | E109: JUANITO C. VALONES | G109: ROBERTO J. DELA CRUZ
A110: Accounting Proc. A | C110: Head, Billing Unit | E110: O&M Chief | G110: Manager, BANE IMO
A119: Republika ng Pilipinas
A120: National Irrigation Administration
A121: (Pambansang Pangasiwaan ng Patubig)
A122: Bulacan – Aurora – Nueva Ecija Irrigation Management Office
A123: Tambubong, San Rafael, Bulacan
A125: Office Address : Tambubong, San Rafael, Bulacan | G125: Telefax No. (044) 766-3888
A126: Telephone Nos. : (044) 766-3888 | G126: TIN No. 000-578-009-000
A127: Email Address : niabaneimoafs@yahoo.com
A129: STATEMENT OF ACCOUNT
A130: =A12
A132: FARMER CODE NO.: | C132: =C14 | F132: WRFT Div. : | G132: =G14
A133: Lot No.: | C133: =C15 | F133: Area:. | G133: =G15
A134: Name of Landowner: | E134: Address:
A135: Name of Farmers: | C135: =C17 | E135: Address:
A136: Area | B136: C. S. | C136: Rate | D136: Principal | E136: %Penalty | F136: Penalty(Cash) | G136: Total
A137: =A19 | B137: 75-W | C137: =1.1*100 | D137: =A137*C137 | F137: =D137*E137/100 | G137: =D137+F137
A138: =A20 | B138: 76-D | C138: =1.1*150 | D138: =A138*C138 | F138: =D138*E138/100 | G138: =D138+F138
A139: =A21 | B139: 76-W | C139: =1.1*100 | D139: =A139*C139 | F139: =D139*E139/100 | G139: =D139+F139
A140: =A22 | B140: 77-D | C140: =1.1*150 | D140: =A140*C140 | F140: =D140*E140/100 | G140: =D140+F140
A141: =A23 | B141: 77-W | C141: =1.1*100 | D141: =A141*C141 | F141: =D141*E141/100 | G141: =D141+F141
A142: =A24 | B142: 78-D | C142: =1.1*150 | D142: =A142*C142 | F142: =D142*E142/100 | G142: =D142+F142
A143: =A25 | B143: 78-W | C143: =1.1*100 | D143: =A143*C143 | F143: =D143*E143/100 | G143: =D143+F143
A144: =A26 | B144: 79-D | C144: =1.1*150 | D144: =A144*C144 | F144: =D144*E144/100 | G144: =D144+F144
A145: =A27 | B145: 79-W | C145: =1.3*100 | D145: =A145*C145 | F145: =D145*E145/100 | G145: =D145+F145
A146: =A28 | B146: 80-D | C146: =1.3*150 | D146: =A146*C146 | F146: =D146*E146/100 | G146: =D146+F146
A147: =A29 | B147: 80-W | C147: =1.3*100 | D147: =A147*C147 | F147: =D147*E147/100 | G147: =D147+F147
A148: =A30 | B148: 81-D | C148: =1.4*150 | D148: =A148*C148 | F148: =D148*E148/100 | G148: =D148+F148
A149: =A31 | B149: 81-W | C149: =1.45*100 | D149: =A149*C149 | F149: =D149*E149/100 | G149: =D149+F149
A150: =A32 | B150: 82-D | C150: =1.55*150 | D150: =A150*C150 | F150: =D150*E150/100 | G150: =D150+F150
...

Sheet 02 REGISTRY
V1: Form 1
A2: REPUBLIC OF THE PHILIPPINES
A3: NATIONAL IRRIGATION ADMINISTRATION
A4: REGIONAL OFFICE NO. III (CENTRAL LUZON)
A5: BULACAN IRRIGATION MANAGEMENT OFFICE
A10: REGISTRY OF LANDOWNERS, FARMERS, AND OTHER IRRIGATION WATER USERS
A11: ="(1) As of "&TEXT(TODAY(),"mmmm dd, yyyy")
A13: (2) | B13: Region: III | M13: ="(5) Name of IA : "&'00 ACC DETAILS 01'!C5
A14: (3) | B14: IMO: BULACAN | M14: (6) Turnout Service Area Group/Sector No. or Name:
A15: (4) | B15: Name of NIS/CIS: AMRIS | M15: ="(7) Supply Canal: (8) Station : "&'00 ACC DETAILS 01'!C4
A17: Lot Number | C17: Lot Area (ha) | D17: Location of Lot | G17: Proof of Ownership | H17: Name of Landowner | K17: Address of Landowner | N17: Name of Farmer (ActualTiller) or Water User | Q17: Address of Farmer (ActualTiller) or Water User | T17: Status of Exemption | V17: REMARKS
C19: (10) | D19: Barangay | E19: Municipality/ City | F19: Province | G19: (12) | H19: Family Name | I19: First Name | J19: Middle Name | K19: Barangay | L19: Municipality/ City | M19: Province | N19: Family Name | O19: First Name | P19: Middle Name | Q19: Barangay | R19: Municipality/ City | S19: Province | T19: Exempted | U19: Not Exempted
A20: (9) | C20: (10) | D20: (11) | E20: (12) | F20: (13) | G20: (14) | H20: (15) | I20: (16) | J20: (17) | K20: (18) | L20: (19) | M20: (20) | N20: (21) | O20: (22) | P20: (23) | Q20: (24) | R20: (25) | S20: (26) | T20: (27) | U20: (28) | V20: (29)
A21: ='00 ACC DETAILS 01'!C3 | C21: ='01 SOA 01'!G13 | D21: ='00 ACC DETAILS 01'!C15 | E21: ='00 ACC DETAILS 01'!C16 | F21: ='00 ACC DETAILS 01'!C17 | H21: ='00 ACC DETAILS 01'!C9 | I21: ='00 ACC DETAILS 01'!C7 | J21: ='00 ACC DETAILS 01'!C8 | K21: ='00 ACC DETAILS 01'!C19 | L21: ='00 ACC DETAILS 01'!C20 | M21: ='00 ACC DETAILS 01'!C21 | N21: ='00 ACC DETAILS 01'!C13 | O21: ='00 ACC DETAILS 01'!C11 | P21: ='00 ACC DETAILS 01'!C12 | Q21: ='00 ACC DETAILS 01'!C23 | R21: ='00 ACC DETAILS 01'!C24 | S21: ='00 ACC DETAILS 01'!C25 | T21: ü
A22: ='00 ACC DETAILS 02'!C3 | C22: ='01 SOA 02'!G15 | D22: ='00 ACC DETAILS 02'!C15 | E22: ='00 ACC DETAILS 02'!C16 | F22: ='00 ACC DETAILS 02'!C17 | H22: ='00 ACC DETAILS 02'!C9 | I22: ='00 ACC DETAILS 02'!C7 | J22: ='00 ACC DETAILS 02'!C8 | K22: ='00 ACC DETAILS 02'!C19 | L22: ='00 ACC DETAILS 02'!C20 | M22: ='00 ACC DETAILS 02'!C21 | N22: ='00 ACC DETAILS 02'!C13 | O22: ='00 ACC DETAILS 02'!C11 | P22: ='00 ACC DETAILS 02'!C12 | Q22: ='00 ACC DETAILS 02'!C23 | R22: ='00 ACC DETAILS 02'!C24 | S22: ='00 ACC DETAILS 02'!C25 | T22: ü
A23: ='00 ACC DETAILS 03'!C3 | C23: ='01 SOA 03'!G15 | D23: ='00 ACC DETAILS 03'!C15 | E23: ='00 ACC DETAILS 03'!C16 | F23: ='00 ACC DETAILS 03'!C17 | H23: ='00 ACC DETAILS 03'!C9 | I23: ='00 ACC DETAILS 03'!C7 | J23: ='00 ACC DETAILS 03'!C8 | K23: ='00 ACC DETAILS 03'!C19 | L23: ='00 ACC DETAILS 03'!C20 | M23: ='00 ACC DETAILS 03'!C21 | N23: ='00 ACC DETAILS 03'!C13 | O23: ='00 ACC DETAILS 03'!C11 | P23: ='00 ACC DETAILS 03'!C12 | Q23: ='00 ACC DETAILS 03'!C23 | R23: ='00 ACC DETAILS 03'!C24 | S23: ='00 ACC DETAILS 03'!C25 | T23: ü
A24: ='00 ACC DETAILS 04'!C3 | C24: ='01 SOA 04'!G15 | D24: ='00 ACC DETAILS 04'!C15 | E24: ='00 ACC DETAILS 04'!C16 | F24: ='00 ACC DETAILS 04'!C17 | H24: ='00 ACC DETAILS 04'!C9 | I24: ='00 ACC DETAILS 04'!C7 | J24: ='00 ACC DETAILS 04'!C8 | K24: ='00 ACC DETAILS 04'!C19 | L24: ='00 ACC DETAILS 04'!C20 | M24: ='00 ACC DETAILS 04'!C21 | N24: ='00 ACC DETAILS 04'!C13 | O24: ='00 ACC DETAILS 04'!C11 | P24: ='00 ACC DETAILS 04'!C12 | Q24: ='00 ACC DETAILS 04'!C23 | R24: ='00 ACC DETAILS 04'!C24 | S24: ='00 ACC DETAILS 04'!C25 | T24: ü
A25: ='00 ACC DETAILS 05'!C3 | C25: ='01 SOA 05'!G15 | D25: ='00 ACC DETAILS 05'!C15 | E25: ='00 ACC DETAILS 05'!C16 | F25: ='00 ACC DETAILS 05'!C17 | H25: ='00 ACC DETAILS 05'!C9 | I25: ='00 ACC DETAILS 05'!C7 | J25: ='00 ACC DETAILS 05'!C8 | K25: ='00 ACC DETAILS 05'!C19 | L25: ='00 ACC DETAILS 05'!C20 | M25: ='00 ACC DETAILS 05'!C21 | N25: ='00 ACC DETAILS 05'!C13 | O25: ='00 ACC DETAILS 05'!C11 | P25: ='00 ACC DETAILS 05'!C12 | Q25: ='00 ACC DETAILS 05'!C23 | R25: ='00 ACC DETAILS 05'!C24 | S25: ='00 ACC DETAILS 05'!C25 | T25: ü
A27: TOTAL | C27: =SUM(C21:C26)
A29: Prepared by: | I29: Submitted by: | Q29: Approved by:
C31: CATHERINE DC. AUSTRIA | J31: LEOPOLDO Q. MANIEGO | R31: ROBERTO J. DELA CRUZ
C32: Accounting Processor A | J32: Chief, O & M Section | R32: Manager, BULACAN IMO

Sheet 03 PARTIAL LIST
A1: PARTIAL LIST OF FARMERS AVAIL FOR CONDONATION
A3: ="DIVISION "&'00 ACC DETAILS 01'!C4
A4: LOT NO. | B4: AREA | C4: LANDOWNER | D4: TILLER | E4: UNPAID ISF
E5: PRINCIPAL | F5: PENALTY | G5: PRIOR | H5: TOTAL
A6: ='00 ACC DETAILS 01'!C3 | B6: ='01 SOA 01'!G13 | C6: ='01 SOA 01'!C14 | D6: ='01 SOA 01'!C15 | E6: ='01 SOA 01'!D100 | F6: ='01 SOA 01'!F100 | G6: ='01 SOA 01'!G101 | H6: ='01 SOA 01'!G100
A7: ='00 ACC DETAILS 02'!C3 | B7: ='01 SOA 02'!G15 | C7: ='01 SOA 02'!C16 | D7: ='01 SOA 02'!C17 | E7: ='01 SOA 02'!D102 | F7: ='01 SOA 02'!F102 | G7: ='01 SOA 02'!G103 | H7: ='01 SOA 02'!G102
A8: ='00 ACC DETAILS 03'!C3 | B8: ='01 SOA 03'!G15 | C8: ='01 SOA 03'!C16 | D8: ='01 SOA 03'!C17 | E8: ='01 SOA 03'!D102 | F8: ='01 SOA 03'!F102 | G8: ='01 SOA 03'!G103 | H8: ='01 SOA 03'!G102
A9: ='00 ACC DETAILS 04'!C3 | B9: ='01 SOA 04'!G15 | C9: ='01 SOA 04'!C16 | D9: ='01 SOA 04'!C17 | E9: ='01 SOA 04'!D102 | F9: ='01 SOA 04'!F102 | G9: ='01 SOA 04'!G103 | H9: ='01 SOA 04'!G102
A10: ='00 ACC DETAILS 05'!C3 | B10: ='01 SOA 05'!G15 | C10: ='01 SOA 05'!C16 | D10: ='01 SOA 05'!C17 | E10: ='01 SOA 05'!D102 | F10: ='01 SOA 05'!F102 | G10: ='01 SOA 05'!G103 | H10: ='01 SOA 05'!G102
A12: TOTAL | B12: =SUM(B6:B11) | E12: =SUM(E6:E11) | F12: =SUM(F6:F11) | G12: =SUM(G6:G11) | H12: =SUM(H6:H11)
A15: Prepared by: | C15: Submitted by: | F15: Approved by:
A18: CATHERINE DC. AUSTRIA | D18: LEOPOLDO Q. MANIEGO | G18: ROBERTO J. DELA CRUZ
A19: Accounting Processor A | D19: Chief, O & M Section | G19: Manager, BULACAN IMO

Sheet 04 IRR FISA FORM 2
A1: REPUBLIC OF THE PHILIPPINES
A2: NATIONAL IRRIGATION ADMINISTRATION
A3: REGIONAL OFFICE NO. III (CENTRAL LUZON)
A4: BULACAN IRRIGATION MANAGEMENT OFFICE
Y7: IRR FISA Form 2
A9: STATEMENT OF ACCOUNT FOR UNPAID IRRIGATION SERVICE FEE (ISF) OF EXEMPT LANDOWNERS/FARMERS PER RA 10969 as of February 24, 2018
A11: Name of Irrigation System: AMRIS
A12: IMO: BULACAN IMO
A13: Region: III
A14: Name of Landowner (First, Middle, Family): | L14: ='03 PARTIAL LIST'!C6
A15: Address of Landowner (Barangay, Municipality/City, Province): | Q15: =PROPER('00 ACC DETAILS 01'!C19&", "&'00 ACC DETAILS 01'!C20&", "&'00 ACC DETAILS 01'!C21)
A16: Name of Actual Tiller/Farmer (First, Middle, Family): | N16: ='03 PARTIAL LIST'!D6
A17: Address of Actual Tiller/Farmer (Barangay, Municipality/City, Province): | S17: =PROPER('00 ACC DETAILS 01'!C23&", "&'00 ACC DETAILS 01'!C24&", "&'00 ACC DETAILS 01'!C25)
A19: LOT NO. | C19: AREA | E19: Location of Lot (Barangay, Municipality/City, Province) | Q19: Accumulated Unpaid ISF (P) 1/
Q20: PRINCIPAL | U20: INTEREST | W20: PENALTIES | Z20: TOTAL
A21: ='03 PARTIAL LIST'!A6 | C21: ='03 PARTIAL LIST'!B6 | E21: =PROPER('02 REGISTRY'!D21&", "&'02 REGISTRY'!E21&", "&'02 REGISTRY'!F21) | Q21: ='03 PARTIAL LIST'!E6 | T21: ='03 PARTIAL LIST'!F6 | W21: ='03 PARTIAL LIST'!G6 | Z21: ='03 PARTIAL LIST'!H6
A22: ='03 PARTIAL LIST'!A7 | C22: ='03 PARTIAL LIST'!B7 | E22: =PROPER('02 REGISTRY'!D22&", "&'02 REGISTRY'!E22&", "&'02 REGISTRY'!F22) | Q22: ='03 PARTIAL LIST'!E7 | T22: ='03 PARTIAL LIST'!F7 | W22: ='03 PARTIAL LIST'!G7 | Z22: ='03 PARTIAL LIST'!H7
A23: ='03 PARTIAL LIST'!A8 | C23: ='03 PARTIAL LIST'!B8 | E23: =PROPER('02 REGISTRY'!D23&", "&'02 REGISTRY'!E23&", "&'02 REGISTRY'!F23) | Q23: ='03 PARTIAL LIST'!E8 | T23: ='03 PARTIAL LIST'!F8 | W23: ='03 PARTIAL LIST'!G8 | Z23: ='03 PARTIAL LIST'!H8
A24: ='03 PARTIAL LIST'!A9 | C24: ='03 PARTIAL LIST'!B9 | E24: =PROPER('02 REGISTRY'!D24&", "&'02 REGISTRY'!E24&", "&'02 REGISTRY'!F24) | Q24: ='03 PARTIAL LIST'!E9 | T24: ='03 PARTIAL LIST'!F9 | W24: ='03 PARTIAL LIST'!G9 | Z24: ='03 PARTIAL LIST'!H9
A25: ='03 PARTIAL LIST'!A10 | C25: ='03 PARTIAL LIST'!B10 | E25: =PROPER('02 REGISTRY'!D25&", "&'02 REGISTRY'!E25&", "&'02 REGISTRY'!F25) | Q25: ='03 PARTIAL LIST'!E10 | T25: ='03 PARTIAL LIST'!F10 | W25: ='03 PARTIAL LIST'!G10 | Z25: ='03 PARTIAL LIST'!H10
A27: TOTAL | C27: =SUM(C21:C26) | Q27: =SUM(Q21:Q26) | T27: =SUM(T21:T26) | W27: =SUM(W21:W26) | Z27: =SUM(Z21:Z26)
B32: Prepared by: | S32: Checked by:
F35: CATHERINE DC. AUSTRIA | W35: LEOPOLDO Q. MANIEGO
F36: Bookkeeper/Billing Clerk | W36: Chief, O & M Section
F37: (Signature above printed name) | W37: (Signature above printed name)
J40: Approved by:
N43: ROBERTO J. DELA CRUZ
N44: Manager, BULACAN IMO
N45: (Signature above printed name)

Sheet 05 IRR FISA FORM 3
A1: REPUBLIC OF THE PHILIPPINES
A2: NATIONAL IRRIGATION ADMINISTRATION
A3: REGIONAL OFFICE NO. III (CENTRAL LUZON)
A4: BULACAN IRRIGATION MANAGEMENT OFFICE
Y6: IRR FISA Form 3
A8: REQUEST FOR CONDONATION AND WRITING OFF OF UNPAID IRRIGATION SERVICE FEE PER RA 10969
A10: This is to acknowledge the correctness of the statement of account for unpaid ISF shown in the attached IRR FISA Form 2 as of the date indicated thereat.
A13: This is to likewise attest that my landholding / (landholdings of landowner) covered by the service area of any National Irrigation System or Communal Irrigation System is:
C16: 1. | D16: Not more than eight (8) hectares in aggregate, regardless of location, and not necessary contiguous Farm lots;
C19: 2. | D19: Not a corporate farm or plantation;
C21: 3. | D21: Not a fishpond or for other non-agricultural crop use; and
C23: 4. | D23: Not using the irrigation system as drainage facilities.
C25: In view hereof, may I request that said unpaid ISF be condoned and written off from the books of the National Irrigation Administration per section 4 of Republic Act 10969 otherwise known as the Free Irrigation Service Act (FISA).
A30: Requested by:
A33: __________________________________________________
A34: Name of Landowner/Name of Actual Tiller
A35: (Signature above printed name*Anyone may Request & sign)
B39: Recommending Approval: | S39: Approved by:
F42: ROBERTO J. DELA CRUZ | W42: JOSEPHINE B. SALAZAR
F43: Manager, BULACAN IMO | W43: Regional Irrigation Manager
F44: (Signature above printed name) | W44: (Signature above printed name)

Sheet 06 ACKNOWLEDGEMENT
A2: ACKNOWLEDGEMENT
A5: REPUBLIC OF THE PHILIPPINES )) SS
A7: BEFORE ME, this _____ day of _________________, 20_______, personally appeared:
A9: Name | K9: CTC No. | V9: Date/Place Issued
A11: =IF(ISNUMBER('00 ACC DETAILS 01'!G5),'00 ACC DETAILS 01'!G4&" "&'00 ACC DETAILS 01'!G6,'00 ACC DETAILS 01'!G4&" "&'00 ACC DETAILS 01'!G5&" "&'00 ACC DETAILS 01'!G6)
A17: Known to me and known to be the same persons who executed the foregoing instrument of _____ (4) pages including this page of acknowledgement, and acknowledged to me that the same is their free and voluntary act and deed, as well as the free and voluntary act and deed of the principals they represent.
A22: IN TESTIMONY WHEREOF, I have hereunto set my hand and affixed my notarial seal at the place and on the date first above written.
AB34: NOTARY PUBLIC
A36: Doc. No. _________________;
A37: Page No. _________________;
A38: Book No. ________________;
A39: Series of _______________

Sheet 07 IRR FISA FORM 6
A1: REPUBLIC OF THE PHILIPPINES
A2: NATIONAL IRRIGATION ADMINISTRATION
A3: REGIONAL OFFICE NO. III (CENTRAL LUZON)
A4: BULACAN IRRIGATION MANAGEMENT OFFICE
Y6: IRR FISA Form 6
A8: LANDOWNER’S DECLARATION AND REQUEST FOR ISSUANCE OF CERTIFICATE OF EXEMPTION IN THE PAYMENT OF IRRIGATION SERVICE FEE
A10: This is to declare that my landholding covered by the service area of any National Irrigation System or Communal Irrigation System as of February 24, 2018 – the date of effectivity of RA 10969 otherwise known as the Free Irrigation Service Act (FISA) – is:
A14: This is to likewise attest that my landholding / (landholdings of landowner) covered by the service area of any National Irrigation System or Communal Irrigation System is:
C17: 1. | D17: Not more than eight (8) hectares in aggregate, regardless of location, and not necessarily contiguous farm lots;
C20: 2. | D20: Not a corporate farm or plantation;
C22: 3. | D22: Not a fishpond or for other non-agricultural crop use; and
C24: 4. | D24: Not using the irrigation system as drainage facilities.
A26: I further attest that I shall be held liable for any misdeclaration regarding said landholding.
A28: In view hereof, may I request for the issuance of Certificate of Exemption in the Payment of Irrigation Service Fee for my landholding/s described above.
A32: ____________________________________________________________
A33: Name of Landowner/Name of Actual Tiller
A34: (Signature above printed name*Anyone may Request & sign)

Sheet 08 IRR FISA FORM 7
A1: REPUBLIC OF THE PHILIPPINES
A2: NATIONAL IRRIGATION ADMINISTRATION
A3: REGIONAL OFFICE NO. III (CENTRAL LUZON)
A4: BULACAN IRRIGATION MANAGEMENT OFFICE
Y7: IRR FISA Form 7
A9: CERTIFICATE OF EXEMPTION IN THE PAYMENT OF IRRIGATION SERVICE FEE
A12: Based on the Registry of Landowners, Farmers, and Other Irrigation Water Users (IRR FISA Form 1) of this Office, and the attached Landowner’s Declaration (IRR FISA Form 6), the landholding owned by Mr. /Mrs. /Ms. ANTONIO SALAS with address at): San Isidro, San Luis, Pampanga is EXEMPTED in the payment of Irrigation Service Fee per RA 10969 otherwise known as the Free Irrigation Service Act (FISA). | AC12: =" Based on the Registry of Landowners, Farmers, and Other Irrigation Water Users (IRR FISA Form 1) of this Office, and the attached Landowner’s Declaration (IRR FISA Form 6), the landholding owned by Mr. /Mrs. /Ms. "&IF(ISNUMBER('00 ACC DETAILS 01'!G5),'00 ACC DETAILS 01'!G4&" "&'00 ACC DETAILS 01'!G6,'00 ACC DETAILS 01'!G4&" "&'00 ACC DETAILS 01'!G5&" "&'00 ACC DETAILS 01'!G6)&" with address at): "&PROPER('00 ACC DETAILS 01'!G8&", "&'00 ACC DETAILS 01'!G9&", "&'00 ACC DETAILS 01'!G10)&" is EXEMPTED in the payment of Irrigation Service Fee per RA 10969 otherwise known as the Free Irrigation Service Act (FISA)."
A20: This certification is issued to Mr. /Mrs. /Ms. ANTONIO SALAS on _____________________________, 2022 at Tambubong, San Rafael, Bulacan for whatever legal purpose it may serve. | AC20: =" This certification is issued to Mr. /Mrs. /Ms. "&IF(ISNUMBER('00 ACC DETAILS 01'!G5),'00 ACC DETAILS 01'!G4&" "&'00 ACC DETAILS 01'!G6,'00 ACC DETAILS 01'!G4&" "&'00 ACC DETAILS 01'!G5&" "&'00 ACC DETAILS 01'!G6)&" on _____________________________, 2022 at Tambubong, San Rafael, Bulacan for whatever legal purpose it may serve."
B29: Recommending Approval: | S29: Approved by:
F32: ROBERTO J. DELA CRUZ | W32: JOSEPHINE B. SALAZAR
F33: Manager, BULACAN IMO | W33: Regional Irrigation Manager
F34: (Signature above printed name) | W34: (Signature above printed name)
